Workbook

Sheet Dashboard
B2: DASHBOARD AUTOMATIZADO - GOLDEN HOME
B4: PROYECCIÓN DE VENTAS (STOCK) | E4: DETALLE INSUMOS POR MES | H4: RESUMEN FINANCIERO (REAL)
B5: Total Venta Efectivo | C5: =SUM(Ingreso!K:K) -> 2198610 | E5: Mes | F5: Total Acumulado | H5: Ingresos Totales (Ventas) | I5: =SUM(ventas!D:D) -> 826400
B6: Total Venta Pagina | C6: =SUM(Ingreso!L:L) -> 2049510 | E6: Abril-2026 | F6: =SUMIF(insumos!D:D, E6, insumos!C:C) -> 113379 | H6: Ganancia Real (Post Imp.) | I6: =SUM(ventas!G:G) -> 245269.74
E7: Mayo-2026 | F7: =SUMIF(insumos!D:D, E7, insumos!C:C) -> 29550
B8: COSTOS CONSOLIDADOS | E8: Junio-2026 | F8: =SUMIF(insumos!D:D, E8, insumos!C:C) -> 0 | H8: VENTAS POR MEDIO DE PAGO
B9: Costo Mercadería (Stock) | C9: =SUM(Ingreso!I:I) -> 981610 | E9: Julio-2026 | F9: =SUMIF(insumos!D:D, E9, insumos!C:C) -> 0 | H9: Efectivo | I9: =SUMIF(ventas!E:E, H9, ventas!D:D) -> 36860
B10: Costo Insumos (Total) | C10: =SUM(insumos!C:C) -> 142929 | H10: Tarjeta | I10: =SUMIF(ventas!E:E, H10, ventas!D:D) -> 128910
B11: TOTAL COSTOS OPERATIVOS | C11: =C9 + C10 -> 1124539 | H11: Transferencia | I11: =SUMIF(ventas!E:E, H11, ventas!D:D) -> 82450
H13: IMPUESTO A PAGAR (SII - 19%)
B14: ANÁLISIS DE GESTIÓN Y STOCK | H14: Total Impuesto Acumulado | I14: =SUM(ventas!H:H) -> 58318.6
B15: Unidades Vendidas | C15: =SUM(ventas!C:C) -> 143
B16: Unidades en Stock | C16: =SUM(Ingreso!H:H) -> 552 | H16: COMISIONES MERCADO PAGO (2.6%)
B17: Total Unidades Entradas | C17: =C15+C16 -> 695 | H17: Total Pagado a MP | I17: =SUM(ventas!I:I) -> 3351.66
B18: Distribución: % Vendido | C18: =IF(C17>0, C15/C17, 0) -> 0.2057554
B19: Distribución: % en Stock | C19: =IF(C17>0, C16/C17, 0) -> 0.7942446

Sheet Seleccion
B1: descripcion | C1: sku | D1: costo | E1: unidades
A2: Baoma | B2: Cafetera por goteo 500ml | D2: 6100 | E2: 12 | F2: =D2*E2 -> 73200
A3: Lucky House | B3: Dispensador agua electrico | C3: 24786 | D3: 1800 | E3: 12 | F3: =D3*E3 -> 21600
B4: escurridor plato 1 piso | C4: 23758 | D4: 3000 | E4: 3 | F4: =D4*E4 -> 9000
B5: Escurridor plato 3 pisos | C5: 24527 | D5: 12000 | E5: 3 | F5: =D5*E5 -> 36000
B6: Escurridor plato 2 pisos | C6: 25278 | D6: 10000 | E6: 3 | F6: =D6*E6 -> 30000
B7: Escurridor Cubierto | C7: 24765 | D7: 2500 | E7: 6 | F7: =D7*E7 -> 15000
B8: Estante Organizador 3 niveles ruedas (blanco y negro) | C8: 26332 | D8: 4000 | E8: 8 | F8: =D8*E8 -> 32000
B9: Organizador Maquillaje Blanco | C9: 2724 | D9: 2000 | E9: 10 | F9: =D9*E9 -> 20000
B10: Termo Agua Caliente 1,9L | C10: 318cc-1 | D10: 6500 | F10: =D10*E10 -> 0
B11: Frutero 2 pisos | C11: 24581 | D11: 4000 | E11: 6 | F11: =D11*E11 -> 24000
B12: Organizador Maquillaje Blanco Espejo MDF | C12: 24815 | D12: 2500 | E12: 6 | F12: =D12*E12 -> 15000
A13: Homey | B13: Zapatero Metalico 5 pisos 41*19*71cm | C13: 21454 | D13: 2650 | E13: 10 | F13: =D13*E13 -> 26500
B14: Zapatero Metalico 4 Pisos 41*18,5*50,5cm | C14: 21455 | D14: 1750 | E14: 10 | F14: =D14*E14 -> 17500
B15: Cesta Ropa Cuadrada 41*32*53cm | C15: 51248 | D15: 3000 | E15: 6 | F15: =D15*E15 -> 18000
B16: Cesta Ropa Cuadrada Rigida 42*30*56cm | C16: 23565 | D16: 7000 | E16: 6 | F16: =D16*E16 -> 42000
B17: Cesta Ropa Infantil Diseños 35x45cm | C17: 26135 | D17: 2300 | E17: 8 | F17: =D17*E17 -> 18400
B18: Cesta Ropa Redonda Diseños 35x45cm | C18: 51254 | D18: 2850 | E18: 8 | F18: =D18*E18 -> 22800
A19: huamao | B19: Frutero Metalico Basico Negro 27.5*7cm | C19: 802513 | D19: 1650 | E19: 6 | F19: =D19*E19 -> 9900
B20: Porta Cubierto Negro 19*11cm | C20: 82462 | D20: 1680 | E20: 6 | F20: =D20*E20 -> 10080
B21: Porta Nova Negro 32*15cm | C21: 102307 | D21: 1280 | E21: 6 | F21: =D21*E21 -> 7680
A22: Cosmiva | B22: Set Cintillo y Esponjas 9pcs | C22: AGE697 | D22: 2300 | E22: 12 | F22: =D22*E22 -> 27600
B23: Set Cintillo y Tiburon 16pcs | C23: AGE696 | D23: 2500 | E23: 12 | F23: =D23*E23 -> 30000
B24: Set Tiburon y Esponjas 5pcs | C24: 70086 | D24: 950 | E24: 12 | F24: =D24*E24 -> 11400
A25: Max belleza | B25: Serum Vitamina C 50ml | C25: MB058117 | D25: 1700 | E25: 12 | F25: =D25*E25 -> 20400
B26: Crema Vitamica C 50g | C26: MB058116 | D26: 2200 | E26: 12 | F26: =D26*E26 -> 26400
A27: yimi | B27: Dispensador aceite 470ml 8*19,8cm | C27: 25495 | D27: 1450 | E27: 12 | F27: =D27*E27 -> 17400
A28: Medimake | B28: Masajeador Electrico Recargable | C28: XF-69 | D28: 1000 | E28: 12 | F28: =D28*E28 -> 12000
B29: Masajeador Facial Hielo | C29: 13465 | D29: 1000 | E29: 20 | F29: =D29*E29 -> 20000
F30: =SUM(F2:F29) -> 613860

Sheet insumos
A1: REGISTRO DETALLADO DE INSUMOS
A3: Fecha | B3: Item | C3: Costo | D3: Mes (Auto)
A4: 46127 | B4: Carro compra | C4: 16500 | D4: =TEXT(A4, "MMMM-YYYY") -> abril-2026
A5: 46127 | B5: Bolsa Tela 50und. | C5: 7000 | D5: =TEXT(A5, "MMMM-YYYY") -> abril-2026
A6: 46127 | B6: Estacionamiento | C6: 8000 | D6: =TEXT(A6, "MMMM-YYYY") -> abril-2026
A7: 46127 | B7: Bencina y Tag | C7: 18600 | D7: =TEXT(A7, "MMMM-YYYY") -> abril-2026
A8: 46132 | B8: Papel Film | C8: 7789 | D8: =IF(A8<>"", TEXT(A8, "MMMM-YYYY"), "") -> abril-2026
A9: 46137 | B9: Photoroom | C9: 44490 | D9: =IF(A9<>"", TEXT(A9, "MMMM-YYYY"), "") -> abril-2026
A10: 46137 | B10: Tarjetas impresas | C10: 11000 | D10: =IF(A10<>"", TEXT(A10, "MMMM-YYYY"), "") -> abril-2026
A11: 46147 | B11: Mantel Tela | C11: 2950 | D11: =IF(A11<>"", TEXT(A11, "MMMM-YYYY"), "") -> mayo-2026
A12: 46147 | B12: Estacionamiento | C12: 8000 | D12: =IF(A12<>"", TEXT(A12, "MMMM-YYYY"), "") -> mayo-2026
A13: 46147 | B13: Bencina y Tag | C13: 18600 | D13: =IF(A13<>"", TEXT(A13, "MMMM-YYYY"), "") -> mayo-2026
D14: =IF(A14<>"", TEXT(A14, "MMMM-YYYY"), "")
D15: =IF(A15<>"", TEXT(A15, "MMMM-YYYY"), "")
D16: =IF(A16<>"", TEXT(A16, "MMMM-YYYY"), "")
D17: =IF(A17<>"", TEXT(A17, "MMMM-YYYY"), "")
D18: =IF(A18<>"", TEXT(A18, "MMMM-YYYY"), "")
D19: =IF(A19<>"", TEXT(A19, "MMMM-YYYY"), "")
D20: =IF(A20<>"", TEXT(A20, "MMMM-YYYY"), "")
D21: =IF(A21<>"", TEXT(A21, "MMMM-YYYY"), "")
D22: =IF(A22<>"", TEXT(A22, "MMMM-YYYY"), "")
D23: =IF(A23<>"", TEXT(A23, "MMMM-YYYY"), "")
D24: =IF(A24<>"", TEXT(A24, "MMMM-YYYY"), "")
D25: =IF(A25<>"", TEXT(A25, "MMMM-YYYY"), "")
... D57: =IF(A57<>"", TEXT(A57, "MMMM-YYYY"), "")

Sheet Factor
A2: Rango costo | B2: Factor
A3: $0 – $499 | B3: 3.0×
A4: $500 – $999 | B4: 2.5×
A5: $1.000 – $4.999 | B5: 2.2×
A6: $5.000 – $19.999 | B6: 2.0×
A7: $20.000+ | B7: 1.8×

Sheet Ingreso
A1: PROVEEDOR | B1: SKU | C1: NOMBRE | D1: COSTO | E1: PRECIO | F1: Precio Efectivo (x2) | G1: Precio pagina (x2) | H1: CANTIDAD | I1: Costo total | J1: Venta total (FACTORES) | K1: VENTA (EFECTIVO) | L1: VENTA (PAGINA) | M1: Stock actual
A2: Belina | B2: 1212 | C2: Bolsa Regalo Dia Mamá | D2: 270 | E2: =IF(D2<500,D2*3,IF(D2<1000,D2*2.5,IF(D2<5000,D2*2.2,IF(D2<20000,D2*2,D2*1.8)))) -> 810 | F2: 500 | G2: 500 | H2: 12 | I2: =$D2*$H2 -> 3240 | J2: =$E2*$H2 -> 9720 | K2: =F2*H2 -> 6000 | L2: =G2*H2 -> 6000 | M2: =VLOOKUP($B2,bodega!A:C,3,0) -> 9
A3: Exlin | B3: 809939 | C3: Set de especies 8und bambu | D3: 9000 | E3: =IF(D3<500,D3*3,IF(D3<1000,D3*2.5,IF(D3<5000,D3*2.2,IF(D3<20000,D3*2,D3*1.8)))) -> 18000 | F3: 17990 | G3: =IF(AND(F3>=1000, MOD(F3,1000)<=90), (INT(F3/1000)*1000)-10, ROUNDUP(MAX(0,F3-90),-2)+90) -> 17990 | H3: 3 | I3: =$D3*$H3 -> 27000 | J3: =$E3*$H3 -> 54000 | K3: =F3*H3 -> 53970 | L3: =G3*H3 -> 53970 | M3: =VLOOKUP($B3,bodega!A:C,3,0) -> 0
A4: Exlin | B4: 807597 | C4: Frasco para miel vidrio y bambu | D4: 2600 | E4: =IF(D4<500,D4*3,IF(D4<1000,D4*2.5,IF(D4<5000,D4*2.2,IF(D4<20000,D4*2,D4*1.8)))) -> 5720 | F4: 5290 | G4: =IF(AND(F4>=1000, MOD(F4,1000)<=90), (INT(F4/1000)*1000)-10, ROUNDUP(MAX(0,F4-90),-2)+90) -> 5290 | H4: 13 | I4: =$D4*$H4 -> 33800 | J4: =$E4*$H4 -> 74360 | K4: =F4*H4 -> 68770 | L4: =G4*H4 -> 68770 | M4: =VLOOKUP($B4,bodega!A:C,3,0) -> 7
A5: Exlin | B5: 1515 | C5: Salero y Pimentero Pareja | D5: 2500 | E5: =IF(D5<500,D5*3,IF(D5<1000,D5*2.5,IF(D5<5000,D5*2.2,IF(D5<20000,D5*2,D5*1.8)))) -> 5500 | F5: 4990 | G5: =IF(AND(F5>=1000, MOD(F5,1000)<=90), (INT(F5/1000)*1000)-10, ROUNDUP(MAX(0,F5-90),-2)+90) -> 4990 | H5: 3 | I5: =$D5*$H5 -> 7500 | J5: =$E5*$H5 -> 16500 | K5: =F5*H5 -> 14970 | L5: =G5*H5 -> 14970 | M5: =VLOOKUP($B5,bodega!A:C,3,0) -> 0
A6: Exlin | B6: 1616 | C6: Guatero infantil Patito | D6: 2800 | E6: =IF(D6<500,D6*3,IF(D6<1000,D6*2.5,IF(D6<5000,D6*2.2,IF(D6<20000,D6*2,D6*1.8)))) -> 6160 | F6: 4590 | G6: =IF(AND(F6>=1000, MOD(F6,1000)<=90), (INT(F6/1000)*1000)-10, ROUNDUP(MAX(0,F6-90),-2)+90) -> 4590 | H6: 3 | I6: =$D6*$H6 -> 8400 | J6: =$E6*$H6 -> 18480 | K6: =F6*H6 -> 13770 | L6: =G6*H6 -> 13770 | M6: =VLOOKUP($B6,bodega!A:C,3,0) -> 0
A7: Exlin | B7: 1717 | C7: Guatero Infantil Mounstruito | D7: 2000 | E7: =IF(D7<500,D7*3,IF(D7<1000,D7*2.5,IF(D7<5000,D7*2.2,IF(D7<20000,D7*2,D7*1.8)))) -> 4400 | F7: 4590 | G7: =IF(AND(F7>=1000, MOD(F7,1000)<=90), (INT(F7/1000)*1000)-10, ROUNDUP(MAX(0,F7-90),-2)+90) -> 4590 | H7: 7 | I7: =$D7*$H7 -> 14000 | J7: =$E7*$H7 -> 30800 | K7: =F7*H7 -> 32130 | L7: =G7*H7 -> 32130 | M7: =VLOOKUP($B7,bodega!A:C,3,0) -> 4
A8: Exlin | B8: 808708 | C8: Taza Margarita vidrio | D8: 2000 | E8: =IF(D8<500,D8*3,IF(D8<1000,D8*2.5,IF(D8<5000,D8*2.2,IF(D8<20000,D8*2,D8*1.8)))) -> 4400 | F8: 3990 | G8: =IF(AND(F8>=1000, MOD(F8,1000)<=90), (INT(F8/1000)*1000)-10, ROUNDUP(MAX(0,F8-90),-2)+90) -> 3990 | H8: 6 | I8: =$D8*$H8 -> 12000 | J8: =$E8*$H8 -> 26400 | K8: =F8*H8 -> 23940 | L8: =G8*H8 -> 23940 | M8: =VLOOKUP($B8,bodega!A:C,3,0) -> 0
A9: Exlin | B9: 601873 | C9: Burlete Puerta 95cm | D9: 1000 | E9: =IF(D9<500,D9*3,IF(D9<1000,D9*2.5,IF(D9<5000,D9*2.2,IF(D9<20000,D9*2,D9*1.8)))) -> 2200 | F9: 2490 | G9: =IF(AND(F9>=1000, MOD(F9,1000)<=90), (INT(F9/1000)*1000)-10, ROUNDUP(MAX(0,F9-90),-2)+90) -> 2490 | H9: 6 | I9: =$D9*$H9 -> 6000 | J9: =$E9*$H9 -> 13200 | K9: =F9*H9 -> 14940 | L9: =G9*H9 -> 14940 | M9: =VLOOKUP($B9,bodega!A:C,3,0) -> 4
A10: Exlin | B10: 1313 | C10: Organizador Maquillaje y skincare | D10: 2500 | E10: =IF(D10<500,D10*3,IF(D10<1000,D10*2.5,IF(D10<5000,D10*2.2,IF(D10<20000,D10*2,D10*1.8)))) -> 5500 | F10: 4990 | G10: =IF(AND(F10>=1000, MOD(F10,1000)<=90), (INT(F10/1000)*1000)-10, ROUNDUP(MAX(0,F10-90),-2)+90) -> 4990 | H10: 4 | I10: =$D10*$H10 -> 10000 | J10: =$E10*$H10 -> 22000 | K10: =F10*H10 -> 19960 | L10: =G10*H10 -> 19960 | M10: =VLOOKUP($B10,bodega!A:C,3,0) -> 4
A11: Exlin | B11: 808698 | C11: Taza Flores Doble fondo | D11: 2500 | E11: =IF(D11<500,D11*3,IF(D11<1000,D11*2.5,IF(D11<5000,D11*2.2,IF(D11<20000,D11*2,D11*1.8)))) -> 5500 | F11: 4990 | G11: =IF(AND(F11>=1000, MOD(F11,1000)<=90), (INT(F11/1000)*1000)-10, ROUNDUP(MAX(0,F11-90),-2)+90) -> 4990 | H11: 6 | I11: =$D11*$H11 -> 15000 | J11: =$E11*$H11 -> 33000 | K11: =F11*H11 -> 29940 | L11: =G11*H11 -> 29940 | M11: =VLOOKUP($B11,bodega!A:C,3,0) -> 2
A12: Exlin | B12: 1414 | C12: Posavasos bambu 4und | D12: 1900 | E12: =IF(D12<500,D12*3,IF(D12<1000,D12*2.5,IF(D12<5000,D12*2.2,IF(D12<20000,D12*2,D12*1.8)))) -> 4180 | F12: 3890 | G12: =IF(AND(F12>=1000, MOD(F12,1000)<=90), (INT(F12/1000)*1000)-10, ROUNDUP(MAX(0,F12-90),-2)+90) -> 3890 | H12: 4 | I12: =$D12*$H12 -> 7600 | J12: =$E12*$H12 -> 16720 | K12: =F12*H12 -> 15560 | L12: =G12*H12 -> 15560 | M12: =VLOOKUP($B12,bodega!A:C,3,0) -> 4
A13: Exlin | B13: 655188 | C13: Guatero Conejo 500ml | D13: 2800 | E13: =IF(D13<500,D13*3,IF(D13<1000,D13*2.5,IF(D13<5000,D13*2.2,IF(D13<20000,D13*2,D13*1.8)))) -> 6160 | F13: 4590 | G13: =IF(AND(F13>=1000, MOD(F13,1000)<=90), (INT(F13/1000)*1000)-10, ROUNDUP(MAX(0,F13-90),-2)+90) -> 4590 | H13: 4 | I13: =$D13*$H13 -> 11200 | J13: =$E13*$H13 -> 24640 | K13: =F9*H13 -> 9960 | L13: =G13*H13 -> 18360 | M13: 4
A14: Exlin | B14: 8095749 | C14: Salero y Pimentero Cerditos | D14: 2500 | E14: =IF(D14<500,D14*3,IF(D14<1000,D14*2.5,IF(D14<5000,D14*2.2,IF(D14<20000,D14*2,D14*1.8)))) -> 5500 | F14: 4990 | G14: =IF(AND(F14>=1000, MOD(F14,1000)<=90), (INT(F14/1000)*1000)-10, ROUNDUP(MAX(0,F14-90),-2)+90) -> 4990 | H14: 4 | I14: =$D14*$H14 -> 10000 | J14: =$E14*$H14 -> 22000 | K14: =F10*H14 -> 19960 | L14: =G14*H14 -> 19960 | M14: 4
A15: Homey | B15: 24217 | C15: Cesta Ropa Dinosaurio 40*50cm | D15: 2550 | E15: =IF(D15<500,D15*3,IF(D15<1000,D15*2.5,IF(D15<5000,D15*2.2,IF(D15<20000,D15*2,D15*1.8)))) -> 5610 | F15: 5490 | G15: =IF(AND(F15>=1000, MOD(F15,1000)<=90), (INT(F15/1000)*1000)-10, ROUNDUP(MAX(0,F15-90),-2)+90) -> 5490 | H15: 3 | I15: =$D15*$H15 -> 7650 | J15: =$E15*$H15 -> 16830 | K15: =F15*H15 -> 16470 | L15: =G15*H15 -> 16470 | M15: =VLOOKUP($B15,bodega!A:C,3,0) -> 2
A16: Homey | B16: 19571 | C16: Cesta Ropa Cuadrada café con tapa 42*30*56cm | D16: 7600 | E16: =IF(D16<500,D16*3,IF(D16<1000,D16*2.5,IF(D16<5000,D16*2.2,IF(D16<20000,D16*2,D16*1.8)))) -> 15200 | F16: 15290 | G16: =IF(AND(F16>=1000, MOD(F16,1000)<=90), (INT(F16/1000)*1000)-10, ROUNDUP(MAX(0,F16-90),-2)+90) -> 15290 | H16: 12 | I16: =$D16*$H16 -> 91200 | J16: =$E16*$H16 -> 182400 | K16: =F16*H16 -> 183480 | L16: =G16*H16 -> 183480 | M16: =VLOOKUP($B16,bodega!A:C,3,0) -> 7
A17: Homey | B17: 50948 | C17: Salvamantel Metalico 18*18*1,5cm | D17: 1300 | E17: =IF(D17<500,D17*3,IF(D17<1000,D17*2.5,IF(D17<5000,D17*2.2,IF(D17<20000,D17*2,D17*1.8)))) -> 2860 | F17: 2690 | G17: =IF(AND(F17>=1000, MOD(F17,1000)<=90), (INT(F17/1000)*1000)-10, ROUNDUP(MAX(0,F17-90),-2)+90) -> 2690 | H17: 12 | I17: =$D17*$H17 -> 15600 | J17: =$E17*$H17 -> 34320 | K17: =F17*H17 -> 32280 | L17: =G17*H17 -> 32280 | M17: =VLOOKUP($B17,bodega!A:C,3,0) -> 7
A18: Homey | B18: 25936 | C18: Dispensador Lavalozas 18*12cm | D18: 3900 | E18: =IF(D18<500,D18*3,IF(D18<1000,D18*2.5,IF(D18<5000,D18*2.2,IF(D18<20000,D18*2,D18*1.8)))) -> 8580 | F18: 7890 | G18: =IF(AND(F18>=1000, MOD(F18,1000)<=90), (INT(F18/1000)*1000)-10, ROUNDUP(MAX(0,F18-90),-2)+90) -> 7890 | H18: 8 | I18: =$D18*$H18 -> 31200 | J18: =$E18*$H18 -> 68640 | K18: =F18*H18 -> 63120 | L18: =G18*H18 -> 63120 | M18: =VLOOKUP($B18,bodega!A:C,3,0) -> 4
A19: Homey | B19: 15154 | C19: tripack paños de cocina | D19: 2300 | E19: =IF(D19<500,D19*3,IF(D19<1000,D19*2.5,IF(D19<5000,D19*2.2,IF(D19<20000,D19*2,D19*1.8)))) -> 5060 | F19: 4690 | G19: =IF(AND(F19>=1000, MOD(F19,1000)<=90), (INT(F19/1000)*1000)-10, ROUNDUP(MAX(0,F19-90),-2)+90) -> 4690 | H19: 6 | I19: =$D19*$H19 -> 13800 | J19: =$E19*$H19 -> 30360 | K19: =F19*H19 -> 28140 | L19: =G19*H19 -> 28140 | M19: =VLOOKUP($B19,bodega!A:C,3,0) -> 2
A20: Homey | B20: 21455 | C20: Zapatero Negro Plastico Varillas Metalicas 4 pisos 41*18,5*50cm | D20: 1800 | E20: =IF(D20<500,D20*3,IF(D20<1000,D20*2.5,IF(D20<5000,D20*2.2,IF(D20<20000,D20*2,D20*1.8)))) -> 3960 | F20: 4990 | G20: =IF(AND(F20>=1000, MOD(F20,1000)<=90), (INT(F20/1000)*1000)-10, ROUNDUP(MAX(0,F20-90),-2)+90) -> 4990 | H20: 3 | I20: =$D20*$H20 -> 5400 | J20: =$E20*$H20 -> 11880 | K20: =F20*H20 -> 14970 | L20: =G20*H20 -> 14970 | M20: =VLOOKUP($B20,bodega!A:C,3,0) -> 2
A21: Homey | B21: 21457 | C21: Zapatero Blanco Plastico Varillas Metalicas 4 pisos 47*20*53cm | D21: 3000 | E21: =IF(D21<500,D21*3,IF(D21<1000,D21*2.5,IF(D21<5000,D21*2.2,IF(D21<20000,D21*2,D21*1.8)))) -> 6600 | F21: 5990 | G21: =IF(AND(F21>=1000, MOD(F21,1000)<=90), (INT(F21/1000)*1000)-10, ROUNDUP(MAX(0,F21-90),-2)+90) -> 5990 | H21: 2 | I21: =$D21*$H21 -> 6000 | J21: =$E21*$H21 -> 13200 | K21: =F21*H21 -> 11980 | L21: =G21*H21 -> 11980 | M21: =VLOOKUP($B21,bodega!A:C,3,0) -> 2
A22: Homey | B22: 24218 | C22: Cesta Ropa Leon 40*50cm | D22: 2550 | E22: =IF(D22<500,D22*3,IF(D22<1000,D22*2.5,IF(D22<5000,D22*2.2,IF(D22<20000,D22*2,D22*1.8)))) -> 5610 | F22: 5490 | G22: =IF(AND(F22>=1000, MOD(F22,1000)<=90), (INT(F22/1000)*1000)-10, ROUNDUP(MAX(0,F22-90),-2)+90) -> 5490 | H22: 3 | I22: =$D22*$H22 -> 7650 | J22: =$E22*$H22 -> 16830 | K22: =F22*H22 -> 16470 | L22: =G22*H22 -> 16470 | M22: =VLOOKUP($B22,bodega!A:C,3,0) -> 3
A23: Homey | B23: 51248 | C23: Cesta con cierre algodon 41*32*53cm | D23: 3150 | E23: =IF(D23<500,D23*3,IF(D23<1000,D23*2.5,IF(D23<5000,D23*2.2,IF(D23<20000,D23*2,D23*1.8)))) -> 6930 | F23: 6390 | G23: =IF(AND(F23>=1000, MOD(F23,1000)<=90), (INT(F23/1000)*1000)-10, ROUNDUP(MAX(0,F23-90),-2)+90) -> 6390 | H23: 4 | I23: =$D23*$H23 -> 12600 | J23: =$E23*$H23 -> 27720 | K23: =F23*H23 -> 25560 | L23: =G23*H23 -> 25560 | M23: =VLOOKUP($B23,bodega!A:C,3,0) -> 3
A24: Homey | B24: 22489 | C24: Caja organizadora Te 4 compartimiento15*15*7cm | D24: 3100 | E24: =IF(D24<500,D24*3,IF(D24<1000,D24*2.5,IF(D24<5000,D24*2.2,IF(D24<20000,D24*2,D24*1.8)))) -> 6820 | F24: 6290 | G24: =IF(AND(F24>=1000, MOD(F24,1000)<=90), (INT(F24/1000)*1000)-10, ROUNDUP(MAX(0,F24-90),-2)+90) -> 6290 | H24: 4 | I24: =$D24*$H24 -> 12400 | J24: =$E24*$H24 -> 27280 | K24: =F24*H24 -> 25160 | L24: =G24*H24 -> 25160 | M24: =VLOOKUP($B24,bodega!A:C,3,0) -> 3
A25: Homey | B25: 22493 | C25: Caja organizadora Te 6 compartimientos 24*17*7cm | D25: 3500 | E25: =IF(D25<500,D25*3,IF(D25<1000,D25*2.5,IF(D25<5000,D25*2.2,IF(D25<20000,D25*2,D25*1.8)))) -> 7700 | F25: 6990 | G25: =IF(AND(F25>=1000, MOD(F25,1000)<=90), (INT(F25/1000)*1000)-10, ROUNDUP(MAX(0,F25-90),-2)+90) -> 6990 | H25: 4 | I25: =$D25*$H25 -> 14000 | J25: =$E25*$H25 -> 30800 | K25: =F25*H25 -> 27960 | L25: =G25*H25 -> 27960 | M25: =VLOOKUP($B25,bodega!A:C,3,0) -> 3
A26: Homey | B26: 23712 | C26: Destapador de botellas Basquetbol 6,5*15*20cm | D26: 2750 | E26: =IF(D26<500,D26*3,IF(D26<1000,D26*2.5,IF(D26<5000,D26*2.2,IF(D26<20000,D26*2,D26*1.8)))) -> 6050 | F26: 5590 | G26: =IF(AND(F26>=1000, MOD(F26,1000)<=90), (INT(F26/1000)*1000)-10, ROUNDUP(MAX(0,F26-90),-2)+90) -> 5590 | H26: 4 | I26: =$D26*$H26 -> 11000 | J26: =$E26*$H26 -> 24200 | K26: =F26*H26 -> 22360 | L26: =G26*H26 -> 22360 | M26: =VLOOKUP($B26,bodega!A:C,3,0) -> 3
... A35: Homey | B35: 22629 | C35: Posavasos Ceramica 11,5cm | D35: 700 | E35: =IF(D35<500,D35*3,IF(D35<1000,D35*2.5,IF(D35<5000,D35*2.2,IF(D35<20000,D35*2,D35*1.8)))) -> 1750 | F35: 1490 | G35: =IF(AND(F35>=1000, MOD(F35,1000)<=90), (INT(F35/1000)*1000)-10, ROUNDUP(MAX(0,F35-90),-2)+90) -> 1490 | H35: 12 | I35: =$D35*$H35 -> 8400 | J35: =$E35*$H35 -> 21000 | K35: =F35*H35 -> 17880 | L35: =G35*H35 -> 17880 | M35: =VLOOKUP($B35,bodega!A:C,3,0) -> 12
A36: Homey | B36: 51027 | C36: Salvamantel Ceramica redondo 16cm | D36: 1200 | E36: =IF(D36<500,D36*3,IF(D36<1000,D36*2.5,IF(D36<5000,D36*2.2,IF(D36<20000,D36*2,D36*1.8)))) -> 2640 | F36: 2690 | G36: =IF(AND(F36>=1000, MOD(F36,1000)<=90), (INT(F36/1000)*1000)-10, ROUNDUP(MAX(0,F36-90),-2)+90) -> 2690 | H36: 4 | I36: =$D36*$H36 -> 4800 | J36: =$E36*$H36 -> 10560 | K36: =F32*H36 -> 6760 | L36: =G36*H36 -> 10760 | M36: 4
A37: Homey | B37: 14806 | C37: Panera Marron ovalada 8x25x31cm | D37: 1500 | E37: =IF(D37<500,D37*3,IF(D37<1000,D37*2.5,IF(D37<5000,D37*2.2,IF(D37<20000,D37*2,D37*1.8)))) -> 3300 | F37: 3390 | G37: =IF(AND(F37>=1000, MOD(F37,1000)<=90), (INT(F37/1000)*1000)-10, ROUNDUP(MAX(0,F37-90),-2)+90) -> 3390 | H37: 3 | I37: =$D37*$H37 -> 4500 | J37: =$E37*$H37 -> 9900 | K37: =F33*H37 -> 17970 | L37: =G37*H37 -> 10170 | M37: 3
A38: Homey | B38: 16935 | C38: Paño secaplato | D38: 1400 | E38: =IF(D38<500,D38*3,IF(D38<1000,D38*2.5,IF(D38<5000,D38*2.2,IF(D38<20000,D38*2,D38*1.8)))) -> 3080 | F38: 2990 | G38: =IF(AND(F38>=1000, MOD(F38,1000)<=90), (INT(F38/1000)*1000)-10, ROUNDUP(MAX(0,F38-90),-2)+90) -> 2990 | H38: 4 | I38: =$D38*$H38 -> 5600 | J38: =$E38*$H38 -> 12320 | K38: =F34*H38 -> 15560 | L38: =G38*H38 -> 11960 | M38: 4
A39: Homey | B39: 7676887207875 | C39: Guatero Electrico Conejo Rosado 26x19cm | D39: 2800 | E39: =IF(D39<500,D39*3,IF(D39<1000,D39*2.5,IF(D39<5000,D39*2.2,IF(D39<20000,D39*2,D39*1.8)))) -> 6160 | F39: 5990 | G39: =IF(AND(F39>=1000, MOD(F39,1000)<=90), (INT(F39/1000)*1000)-10, ROUNDUP(MAX(0,F39-90),-2)+90) -> 5990 | H39: 3 | I39: =$D39*$H39 -> 8400 | J39: =$E39*$H39 -> 18480 | K39: =F35*H39 -> 4470 | L39: =G39*H39 -> 17970 | M39: 3
A40: Homey | B40: 7676887207929 | C40: Guatero Electrico Marron Oso 26x19cm | D40: 2800 | E40: =IF(D40<500,D40*3,IF(D40<1000,D40*2.5,IF(D40<5000,D40*2.2,IF(D40<20000,D40*2,D40*1.8)))) -> 6160 | F40: 5990 | G40: =IF(AND(F40>=1000, MOD(F40,1000)<=90), (INT(F40/1000)*1000)-10, ROUNDUP(MAX(0,F40-90),-2)+90) -> 5990 | H40: 3 | I40: =$D40*$H40 -> 8400 | J40: =$E40*$H40 -> 18480 | K40: =F36*H40 -> 8070 | L40: =G40*H40 -> 17970 | M40: 3
A41: Homey | B41: 15512 | C41: Individual Tejido Negro 38cm | D41: 750 | E41: =IF(D41<500,D41*3,IF(D41<1000,D41*2.5,IF(D41<5000,D41*2.2,IF(D41<20000,D41*2,D41*1.8)))) -> 1875 | F41: 1690 | G41: =IF(AND(F41>=1000, MOD(F41,1000)<=90), (INT(F41/1000)*1000)-10, ROUNDUP(MAX(0,F41-90),-2)+90) -> 1690 | H41: 24 | I41: =$D41*$H41 -> 18000 | J41: =$E41*$H41 -> 45000 | K41: =F37*H41 -> 81360 | L41: =G41*H41 -> 40560 | M41: 24
A42: Homey | B42: 24049 | C42: Camino de mesa blanco gris 35x180cm | D42: 2650 | E42: =IF(D42<500,D42*3,IF(D42<1000,D42*2.5,IF(D42<5000,D42*2.2,IF(D42<20000,D42*2,D42*1.8)))) -> 5830 | F42: 5790 | G42: =IF(AND(F42>=1000, MOD(F42,1000)<=90), (INT(F42/1000)*1000)-10, ROUNDUP(MAX(0,F42-90),-2)+90) -> 5790 | H42: 3 | I42: =$D42*$H42 -> 7950 | J42: =$E42*$H42 -> 17490 | K42: =F38*H42 -> 8970 | L42: =G42*H42 -> 17370 | M42: 3
A43: Homey | B43: 15955 | C43: Individual Plateado PVC 38cm | D43: 650 | E43: =IF(D43<500,D43*3,IF(D43<1000,D43*2.5,IF(D43<5000,D43*2.2,IF(D43<20000,D43*2,D43*1.8)))) -> 1625 | F43: 1690 | G43: =IF(AND(F43>=1000, MOD(F43,1000)<=90), (INT(F43/1000)*1000)-10, ROUNDUP(MAX(0,F43-90),-2)+90) -> 1690 | H43: 24 | I43: =$D43*$H43 -> 15600 | J43: =$E43*$H43 -> 39000 | K43: =F39*H43 -> 143760 | L43: =G43*H43 -> 40560 | M43: 24
A44: Homey | B44: 22815 | C44: Set tabla picar 3pcs 34x24cm | D44: 1400 | E44: =IF(D44<500,D44*3,IF(D44<1000,D44*2.5,IF(D44<5000,D44*2.2,IF(D44<20000,D44*2,D44*1.8)))) -> 3080 | F44: 3990 | G44: =IF(AND(F44>=1000, MOD(F44,1000)<=90), (INT(F44/1000)*1000)-10, ROUNDUP(MAX(0,F44-90),-2)+90) -> 3990 | H44: 5 | I44: =$D44*$H44 -> 7000 | J44: =$E44*$H44 -> 15400 | K44: =F40*H44 -> 29950 | L44: =G44*H44 -> 19950 | M44: 5
A45: Homey | B45: 51028 | C45: Posavasos Ceramica Gato Rosado 10x10cm | D45: 800 | E45: =IF(D45<500,D45*3,IF(D45<1000,D45*2.5,IF(D45<5000,D45*2.2,IF(D45<20000,D45*2,D45*1.8)))) -> 2000 | F45: 1590 | G45: =IF(AND(F45>=1000, MOD(F45,1000)<=90), (INT(F45/1000)*1000)-10, ROUNDUP(MAX(0,F45-90),-2)+90) -> 1590 | H45: 10 | I45: =$D45*$H45 -> 8000 | J45: =$E45*$H45 -> 20000 | K45: =F41*H45 -> 16900 | L45: =G45*H45 -> 15900 | M45: 10
A46: Homey | B46: 51032 | C46: Posavasos Ceramica Gato Capuccino 12.5x12.5cm | D46: 800 | E46: =IF(D46<500,D46*3,IF(D46<1000,D46*2.5,IF(D46<5000,D46*2.2,IF(D46<20000,D46*2,D46*1.8)))) -> 2000 | F46: 1590 | G46: =IF(AND(F46>=1000, MOD(F46,1000)<=90), (INT(F46/1000)*1000)-10, ROUNDUP(MAX(0,F46-90),-2)+90) -> 1590 | H46: 12 | I46: =$D46*$H46 -> 9600 | J46: =$E46*$H46 -> 24000 | K46: =F42*H46 -> 69480 | L46: =G46*H46 -> 19080 | M46: 12
A47: Homey | B47: 11409 | C47: Bolsa lavadora 40x50cm | D47: 750 | E47: =IF(D47<500,D47*3,IF(D47<1000,D47*2.5,IF(D47<5000,D47*2.2,IF(D47<20000,D47*2,D47*1.8)))) -> 1875 | F47: 1890 | G47: =IF(AND(F47>=1000, MOD(F47,1000)<=90), (INT(F47/1000)*1000)-10, ROUNDUP(MAX(0,F47-90),-2)+90) -> 1890 | H47: 6 | I47: =$D47*$H47 -> 4500 | J47: =$E47*$H47 -> 11250 | K47: =F43*H47 -> 10140 | L47: =G47*H47 -> 11340 | M47: 6 | N47: 1 regalo
A48: IRM | B48: XL830L | C48: Humidificador electrico USB | D48: 1900 | E48: =IF(D48<500,D48*3,IF(D48<1000,D48*2.5,IF(D48<5000,D48*2.2,IF(D48<20000,D48*2,D48*1.8)))) -> 4180 | F48: 3890 | G48: =IF(AND(F48>=1000, MOD(F48,1000)<=90), (INT(F48/1000)*1000)-10, ROUNDUP(MAX(0,F48-90),-2)+90) -> 3890 | H48: 11 | I48: =$D48*$H48 -> 20900 | J48: =$E48*$H48 -> 45980 | K48: =F48*H48 -> 42790 | L48: =G48*H48 -> 42790 | M48: =VLOOKUP($B48,bodega!A:C,3,0) -> 5
A49: IRM | B49: 6265 | C49: Dispensador Agua Electrico USB | D49: 2000 | E49: =IF(D49<500,D49*3,IF(D49<1000,D49*2.5,IF(D49<5000,D49*2.2,IF(D49<20000,D49*2,D49*1.8)))) -> 4400 | F49: 3990 | G49: =IF(AND(F49>=1000, MOD(F49,1000)<=90), (INT(F49/1000)*1000)-10, ROUNDUP(MAX(0,F49-90),-2)+90) -> 3990 | H49: 10 | I49: =$D49*$H49 -> 20000 | J49: =$E49*$H49 -> 44000 | K49: =F49*H49 -> 39900 | L49: =G49*H49 -> 39900 | M49: =VLOOKUP($B49,bodega!A:C,3,0) -> 10
A50: IRM | B50: XF-69 | C50: Masajeador Corporal recargable | D50: 1000 | E50: =IF(D50<500,D50*3,IF(D50<1000,D50*2.5,IF(D50<5000,D50*2.2,IF(D50<20000,D50*2,D50*1.8)))) -> 2200 | F50: 2990 | G50: =IF(AND(F50>=1000, MOD(F50,1000)<=90), (INT(F50/1000)*1000)-10, ROUNDUP(MAX(0,F50-90),-2)+90) -> 2990 | H50: 11 | I50: =$D50*$H50 -> 11000 | J50: =$E50*$H50 -> 24200 | K50: =F50*H50 -> 32890 | L50: =G50*H50 -> 32890 | M50: =VLOOKUP($B50,bodega!A:C,3,0) -> 9
A51: IRM | B51: 13465 | C51: Masajeador Facial Hielo | D51: 1000 | E51: =IF(D51<500,D51*3,IF(D51<1000,D51*2.5,IF(D51<5000,D51*2.2,IF(D51<20000,D51*2,D51*1.8)))) -> 2200 | F51: 1990 | G51: =IF(AND(F51>=1000, MOD(F51,1000)<=90), (INT(F51/1000)*1000)-10, ROUNDUP(MAX(0,F51-90),-2)+90) -> 1990 | H51: 15 | I51: =$D51*$H51 -> 15000 | J51: =$E51*$H51 -> 33000 | K51: =F47*H51 -> 28350 | L51: =G51*H51 -> 29850 | M51: =VLOOKUP($B51,bodega!A:C,3,0) -> 14
A52: IRM | B52: 13935 | C52: Espumador de leche electrico | D52: 2300 | E52: =IF(D52<500,D52*3,IF(D52<1000,D52*2.5,IF(D52<5000,D52*2.2,IF(D52<20000,D52*2,D52*1.8)))) -> 5060 | F52: 4990 | G52: =IF(AND(F52>=1000, MOD(F52,1000)<=90), (INT(F52/1000)*1000)-10, ROUNDUP(MAX(0,F52-90),-2)+90) -> 4990 | H52: 5 | I52: =$D52*$H52 -> 11500 | J52: =$E52*$H52 -> 25300 | K52: =F48*H52 -> 19450 | L52: =G52*H52 -> 24950 | M52: 5
A53: IRM | B53: 13517 | C53: Huevera Plastica | D53: 2400 | E53: =IF(D53<500,D53*3,IF(D53<1000,D53*2.5,IF(D53<5000,D53*2.2,IF(D53<20000,D53*2,D53*1.8)))) -> 5280 | F53: 5290 | G53: =IF(AND(F53>=1000, MOD(F53,1000)<=90), (INT(F53/1000)*1000)-10, ROUNDUP(MAX(0,F53-90),-2)+90) -> 5290 | H53: 3 | I53: =$D53*$H53 -> 7200 | J53: =$E53*$H53 -> 15840 | K53: =F49*H53 -> 11970 | L53: =G53*H53 -> 15870 | M53: 3
A54: IRM | B54: 6242 | C54: Caja esencias 12 und 3ml | D54: 1500 | E54: =IF(D54<500,D54*3,IF(D54<1000,D54*2.5,IF(D54<5000,D54*2.2,IF(D54<20000,D54*2,D54*1.8)))) -> 3300 | F54: 2990 | G54: =IF(AND(F54>=1000, MOD(F54,1000)<=90), (INT(F54/1000)*1000)-10, ROUNDUP(MAX(0,F54-90),-2)+90) -> 2990 | H54: 2 | I54: =$D54*$H54 -> 3000 | J54: =$E54*$H54 -> 6600 | K54: =F50*H54 -> 5980 | L54: =G54*H54 -> 5980 | M54: 2
A55: Jumbo | B55: 423722 | C55: Filtro Piscina Bestway v25 | D55: 9990 | E55: =IF(D55<500,D55*3,IF(D55<1000,D55*2.5,IF(D55<5000,D55*2.2,IF(D55<20000,D55*2,D55*1.8)))) -> 19980 | F55: 19990 | G55: =IF(AND(F55>=1000, MOD(F55,1000)<=90), (INT(F55/1000)*1000)-10, ROUNDUP(MAX(0,F55-90),-2)+90) -> 19990 | H55: 1 | I55: =$D55*$H55 -> 9990 | J55: =$E55*$H55 -> 19980 | K55: =F55*H55 -> 19990 | L55: =G55*H55 -> 19990 | M55: =VLOOKUP($B55,bodega!A:C,3,0) -> 1
A56: Jumbo | B56: 423524 | C56: Piscina Inflable Arcoiris 157*46cm | D56: 990 | E56: =IF(D56<500,D56*3,IF(D56<1000,D56*2.5,IF(D56<5000,D56*2.2,IF(D56<20000,D56*2,D56*1.8)))) -> 2475 | F56: 1990 | G56: =IF(AND(F56>=1000, MOD(F56,1000)<=90), (INT(F56/1000)*1000)-10, ROUNDUP(MAX(0,F56-90),-2)+90) -> 1990 | H56: 5 | I56: =$D56*$H56 -> 4950 | J56: =$E56*$H56 -> 12375 | K56: =F56*H56 -> 9950 | L56: =G56*H56 -> 9950 | M56: =VLOOKUP($B56,bodega!A:C,3,0) -> 5
A57: Jumbo | B57: 571010 | C57: Piscina First Fast Set Inflable | D57: 990 | E57: =IF(D57<500,D57*3,IF(D57<1000,D57*2.5,IF(D57<5000,D57*2.2,IF(D57<20000,D57*2,D57*1.8)))) -> 2475 | F57: 1990 | G57: =IF(AND(F57>=1000, MOD(F57,1000)<=90), (INT(F57/1000)*1000)-10, ROUNDUP(MAX(0,F57-90),-2)+90) -> 1990 | H57: 6 | I57: =$D57*$H57 -> 5940 | J57: =$E57*$H57 -> 14850 | K57: =F57*H57 -> 11940 | L57: =G57*H57 -> 11940 | M57: =VLOOKUP($B57,bodega!A:C,3,0) -> 6
A58: Jumbo | B58: 423395 | C58: Sillon Inflable Arcoiris | D58: 1990 | E58: =IF(D58<500,D58*3,IF(D58<1000,D58*2.5,IF(D58<5000,D58*2.2,IF(D58<20000,D58*2,D58*1.8)))) -> 4378 | F58: 3990 | G58: =IF(AND(F58>=1000, MOD(F58,1000)<=90), (INT(F58/1000)*1000)-10, ROUNDUP(MAX(0,F58-90),-2)+90) -> 3990 | H58: 6 | I58: =$D58*$H58 -> 11940 | J58: =$E58*$H58 -> 26268 | K58: =F58*H58 -> 23940 | L58: =G58*H58 -> 23940 | M58: =VLOOKUP($B58,bodega!A:C,3,0) -> 6
A59: Max Belleza | B59: MB090347 | C59: Set Pinche mas esponjas | D59: 1200 | E59: =IF(D59<500,D59*3,IF(D59<1000,D59*2.5,IF(D59<5000,D59*2.2,IF(D59<20000,D59*2,D59*1.8)))) -> 2640 | F59: 2490 | G59: =IF(AND(F59>=1000, MOD(F59,1000)<=90), (INT(F59/1000)*1000)-10, ROUNDUP(MAX(0,F59-90),-2)+90) -> 2490 | H59: 12 | I59: =$D59*$H59 -> 14400 | J59: =$E59*$H59 -> 31680 | K59: =F59*H59 -> 29880 | L59: =G59*H59 -> 29880 | M59: =VLOOKUP($B59,bodega!A:C,3,0) -> 11
A60: Max Belleza | B60: MB058117 | C60: Serum vitamina C 50ml | D60: 2200 | E60: =IF(D60<500,D60*3,IF(D60<1000,D60*2.5,IF(D60<5000,D60*2.2,IF(D60<20000,D60*2,D60*1.8)))) -> 4840 | F60: 4990 | G60: 4990 | H60: 12 | I60: =$D60*$H60 -> 26400 | J60: =$E60*$H60 -> 58080 | K60: =F60*H60 -> 59880 | L60: =G60*H60 -> 59880 | M60: =VLOOKUP($B60,bodega!A:C,3,0) -> 11
A61: Max Belleza | B61: MB058189 | C61: Serum colágeno 50ml | D61: 2100 | E61: =IF(D61<500,D61*3,IF(D61<1000,D61*2.5,IF(D61<5000,D61*2.2,IF(D61<20000,D61*2,D61*1.8)))) -> 4620 | F61: 4990 | G61: 4990 | H61: 12 | I61: =$D61*$H61 -> 25200 | J61: =$E61*$H61 -> 55440 | K61: =F61*H61 -> 59880 | L61: =G61*H61 -> 59880 | M61: =VLOOKUP($B61,bodega!A:C,3,0) -> 12
A62: Max Belleza | B62: MB058116 | C62: Crema vitamina C 50g | D62: 2800 | E62: =IF(D62<500,D62*3,IF(D62<1000,D62*2.5,IF(D62<5000,D62*2.2,IF(D62<20000,D62*2,D62*1.8)))) -> 6160 | F62: 4990 | G62: =IF(AND(F62>=1000, MOD(F62,1000)<=90), (INT(F62/1000)*1000)-10, ROUNDUP(MAX(0,F62-90),-2)+90) -> 4990 | H62: 12 | I62: =$D62*$H62 -> 33600 | J62: =$E62*$H62 -> 73920 | K62: =F62*H62 -> 59880 | L62: =G62*H62 -> 59880 | M62: =VLOOKUP($B62,bodega!A:C,3,0) -> 11
A63: Max Belleza | B63: MB058190 | C63: Crema colágeno 50g | D63: 2100 | E63: =IF(D63<500,D63*3,IF(D63<1000,D63*2.5,IF(D63<5000,D63*2.2,IF(D63<20000,D63*2,D63*1.8)))) -> 4620 | F63: 1990 | G63: =IF(AND(F63>=1000, MOD(F63,1000)<=90), (INT(F63/1000)*1000)-10, ROUNDUP(MAX(0,F63-90),-2)+90) -> 1990 | H63: 12 | I63: =$D63*$H63 -> 25200 | J63: =$E63*$H63 -> 55440 | K63: =F63*H63 -> 23880 | L63: =G63*H63 -> 23880 | M63: =VLOOKUP($B63,bodega!A:C,3,0) -> 12
A64: Max Belleza | B64: MB090333 | C64: Set skincare mas esponjas 6pcs | D64: 1600 | E64: =IF(D64<500,D64*3,IF(D64<1000,D64*2.5,IF(D64<5000,D64*2.2,IF(D64<20000,D64*2,D64*1.8)))) -> 3520 | F64: 3290 | G64: =IF(AND(F64>=1000, MOD(F64,1000)<=90), (INT(F64/1000)*1000)-10, ROUNDUP(MAX(0,F64-90),-2)+90) -> 3290 | H64: 12 | I64: =$D64*$H64 -> 19200 | J64: =$E64*$H64 -> 42240 | K64: =F64*H64 -> 39480 | L64: =G64*H64 -> 39480 | M64: =VLOOKUP($B64,bodega!A:C,3,0) -> 12
A65: Xing Xing | B65: 1010 | C65: Centrifuga para ensaladas | D65: 4800 | E65: =IF(D65<500,D65*3,IF(D65<1000,D65*2.5,IF(D65<5000,D65*2.2,IF(D65<20000,D65*2,D65*1.8)))) -> 10560 | F65: 9690 | G65: =IF(AND(F65>=1000, MOD(F65,1000)<=90), (INT(F65/1000)*1000)-10, ROUNDUP(MAX(0,F65-90),-2)+90) -> 9690 | H65: 6 | I65: =$D65*$H65 -> 28800 | J65: =$E65*$H65 -> 63360 | K65: =F65*H65 -> 58140 | L65: =G65*H65 -> 58140 | M65: =VLOOKUP($B65,bodega!A:C,3,0) -> 2
A66: Xing Xing | B66: 3030 | C66: Botella vidrio para aceite 350ml | D66: 1000 | E66: =IF(D66<500,D66*3,IF(D66<1000,D66*2.5,IF(D66<5000,D66*2.2,IF(D66<20000,D66*2,D66*1.8)))) -> 2200 | F66: 1990 | G66: =IF(AND(F66>=1000, MOD(F66,1000)<=90), (INT(F66/1000)*1000)-10, ROUNDUP(MAX(0,F66-90),-2)+90) -> 1990 | H66: 3 | I66: =$D66*$H66 -> 3000 | J66: =$E66*$H66 -> 6600 | K66: =F66*H66 -> 5970 | L66: =G66*H66 -> 5970 | M66: =VLOOKUP($B66,bodega!A:C,3,0) -> 3
A67: Xing Xing | B67: 5050 | C67: Colador Tela 14cm | D67: 750 | E67: =IF(D67<500,D67*3,IF(D67<1000,D67*2.5,IF(D67<5000,D67*2.2,IF(D67<20000,D67*2,D67*1.8)))) -> 1875 | F67: 1590 | G67: =IF(AND(F67>=1000, MOD(F67,1000)<=90), (INT(F67/1000)*1000)-10, ROUNDUP(MAX(0,F67-90),-2)+90) -> 1590 | H67: 3 | I67: =$D67*$H67 -> 2250 | J67: =$E67*$H67 -> 5625 | K67: =F67*H67 -> 4770 | L67: =G67*H67 -> 4770 | M67: =VLOOKUP($B67,bodega!A:C,3,0) -> 3
A68: Xing Xing | B68: 2020 | C68: Lechero 1200ml | D68: 2000 | E68: =IF(D68<500,D68*3,IF(D68<1000,D68*2.5,IF(D68<5000,D68*2.2,IF(D68<20000,D68*2,D68*1.8)))) -> 4400 | F68: 3990 | G68: =IF(AND(F68>=1000, MOD(F68,1000)<=90), (INT(F68/1000)*1000)-10, ROUNDUP(MAX(0,F68-90),-2)+90) -> 3990 | H68: 9 | I68: =$D68*$H68 -> 18000 | J68: =$E68*$H68 -> 39600 | K68: =F68*H68 -> 35910 | L68: =G68*H68 -> 35910 | M68: =VLOOKUP($B68,bodega!A:C,3,0) -> 6
A69: Xing Xing | B69: 4040 | C69: Balanza Cocina | D69: 2300 | E69: =IF(D69<500,D69*3,IF(D69<1000,D69*2.5,IF(D69<5000,D69*2.2,IF(D69<20000,D69*2,D69*1.8)))) -> 5060 | F69: 4690 | G69: =IF(AND(F69>=1000, MOD(F69,1000)<=90), (INT(F69/1000)*1000)-10, ROUNDUP(MAX(0,F69-90),-2)+90) -> 4690 | H69: 6 | I69: =$D69*$H69 -> 13800 | J69: =$E69*$H69 -> 30360 | K69: =F69*H69 -> 28140 | L69: =G69*H69 -> 28140 | M69: =VLOOKUP($B69,bodega!A:C,3,0) -> 6
A70: Xing Xing | B70: 7070 | C70: Gramera Digital 10kg | D70: 2000 | E70: =IF(D70<500,D70*3,IF(D70<1000,D70*2.5,IF(D70<5000,D70*2.2,IF(D70<20000,D70*2,D70*1.8)))) -> 4400 | F70: 3990 | G70: =IF(AND(F70>=1000, MOD(F70,1000)<=90), (INT(F70/1000)*1000)-10, ROUNDUP(MAX(0,F70-90),-2)+90) -> 3990 | H70: 6 | I70: =$D70*$H70 -> 12000 | J70: =$E70*$H70 -> 26400 | K70: =F70*H70 -> 23940 | L70: =G70*H70 -> 23940 | M70: =VLOOKUP($B70,bodega!A:C,3,0) -> 6
A71: Xing Xing | B71: 6060 | C71: Tostador Mango Madera | D71: 1000 | E71: =IF(D71<500,D71*3,IF(D71<1000,D71*2.5,IF(D71<5000,D71*2.2,IF(D71<20000,D71*2,D71*1.8)))) -> 2200 | F71: 2990 | G71: =IF(AND(F71>=1000, MOD(F71,1000)<=90), (INT(F71/1000)*1000)-10, ROUNDUP(MAX(0,F71-90),-2)+90) -> 2990 | H71: 10 | I71: =$D71*$H71 -> 10000 | J71: =$E71*$H71 -> 22000 | K71: =F71*H71 -> 29900 | L71: =G71*H71 -> 29900 | M71: =VLOOKUP($B71,bodega!A:C,3,0) -> 8
A72: Xing Xing | B72: 3131 | C72: Exprimidor Limon Vidrio | D72: 950 | E72: =IF(D72<500,D72*3,IF(D72<1000,D72*2.5,IF(D72<5000,D72*2.2,IF(D72<20000,D72*2,D72*1.8)))) -> 2375 | F72: 1990 | G72: =IF(AND(F72>=1000, MOD(F72,1000)<=90), (INT(F72/1000)*1000)-10, ROUNDUP(MAX(0,F72-90),-2)+90) -> 1990 | H72: 12 | J72: =$E72*$H72 -> 28500 | K72: =F72*H72 -> 23880 | L72: =G72*H72 -> 23880 | M72: =VLOOKUP($B72,bodega!A:C,3,0) -> 9
A73: Xing Xing | B73: 826840 | C73: Azucarero vidrio relieve | D73: 1200 | E73: =IF(D73<500,D73*3,IF(D73<1000,D73*2.5,IF(D73<5000,D73*2.2,IF(D73<20000,D73*2,D73*1.8)))) -> 2640 | F73: 2690 | G73: =IF(AND(F73>=1000, MOD(F73,1000)<=90), (INT(F73/1000)*1000)-10, ROUNDUP(MAX(0,F73-90),-2)+90) -> 2690 | H73: 4 | I73: =$D73*$H73 -> 4800 | J73: =$E73*$H73 -> 10560 | K73: =F69*H73 -> 18760 | L73: =G73*H73 -> 10760 | M73: =VLOOKUP($B73,bodega!A:C,3,0) -> 4
A74: Xing Xing | B74: 39756 | C74: Sarten de animalitos | D74: 1000 | E74: =IF(D74<500,D74*3,IF(D74<1000,D74*2.5,IF(D74<5000,D74*2.2,IF(D74<20000,D74*2,D74*1.8)))) -> 2200 | F74: 2990 | G74: =IF(AND(F74>=1000, MOD(F74,1000)<=90), (INT(F74/1000)*1000)-10, ROUNDUP(MAX(0,F74-90),-2)+90) -> 2990 | H74: 3 | I74: =$D74*$H74 -> 3000 | J74: =$E74*$H74 -> 6600 | K74: =F70*H74 -> 11970 | L74: =G74*H74 -> 8970 | M74: =VLOOKUP($B74,bodega!A:C,3,0) -> 3
A75: Zheng Chang | B75: 61508 | C75: Tetera Infusora Vidrio | D75: 4350 | E75: =IF(D75<500,D75*3,IF(D75<1000,D75*2.5,IF(D75<5000,D75*2.2,IF(D75<20000,D75*2,D75*1.8)))) -> 9570 | F75: 8590 | G75: =IF(AND(F75>=1000, MOD(F75,1000)<=90), (INT(F75/1000)*1000)-10, ROUNDUP(MAX(0,F75-90),-2)+90) -> 8590 | H75: 4 | I75: =$D75*$H75 -> 17400 | J75: =$E75*$H75 -> 38280 | K75: =F71*H75 -> 11960 | L75: =G75*H75 -> 34360 | M75: =VLOOKUP($B75,bodega!A:C,3,0) -> 2
A76: Tecno | B76: 17709-8 | C76: Cargador Inalambrico Magsafe | D76: 12600 | E76: =IF(D76<500,D76*3,IF(D76<1000,D76*2.5,IF(D76<5000,D76*2.2,IF(D76<20000,D76*2,D76*1.8)))) -> 25200 | F76: 15000 | G76: =IF(AND(F76>=1000, MOD(F76,1000)<=90), (INT(F76/1000)*1000)-10, ROUNDUP(MAX(0,F76-90),-2)+90) -> 14990 | H76: 6 | M76: =VLOOKUP($B76,bodega!A:C,3,0) -> 3
A77: Tecno | B77: 52507 | C77: Audifonos Airpods Pro 2 | D77: 13680 | E77: =IF(D77<500,D77*3,IF(D77<1000,D77*2.5,IF(D77<5000,D77*2.2,IF(D77<20000,D77*2,D77*1.8)))) -> 27360 | F77: 25000 | G77: =IF(AND(F77>=1000, MOD(F77,1000)<=90), (INT(F77/1000)*1000)-10, ROUNDUP(MAX(0,F77-90),-2)+90) -> 24990 | H77: 5 | M77: =VLOOKUP($B77,bodega!A:C,3,0) -> -1

Sheet bodega
A1: CONTROL DE BODEGA - SEMÁFORO DE INGRESO
A3: SKU | B3: Nombre (Ingreso) | C3: Cantidad Disponible
A4: 1212 | B4: =IFERROR(VLOOKUP(A4, Ingreso!$B:$H, 2, FALSE), "Buscando...") -> Bolsa Regalo Dia Mamá | C4: =IFERROR(VLOOKUP(A4, Ingreso!$B:$H, 7, FALSE), 0) - SUMIF(ventas!$A:$A, A4, ventas!$C:$C) -> 9
A5: 809939 | B5: =IFERROR(VLOOKUP(A5, Ingreso!$B:$H, 2, FALSE), "Buscando...") -> Set de especies 8und bambu | C5: =IFERROR(VLOOKUP(A5, Ingreso!$B:$H, 7, FALSE), 0) - SUMIF(ventas!$A:$A, A5, ventas!$C:$C) -> 0
A6: 807597 | B6: =IFERROR(VLOOKUP(A6, Ingreso!$B:$H, 2, FALSE), "Buscando...") -> Frasco para miel vidrio y bambu | C6: =IFERROR(VLOOKUP(A6, Ingreso!$B:$H, 7, FALSE), 0) - SUMIF(ventas!$A:$A, A6, ventas!$C:$C) -> 7
A7: 1515 | B7: =IFERROR(VLOOKUP(A7, Ingreso!$B:$H, 2, FALSE), "Buscando...") -> Salero y Pimentero Pareja | C7: =IFERROR(VLOOKUP(A7, Ingreso!$B:$H, 7, FALSE), 0) - SUMIF(ventas!$A:$A, A7, ventas!$C:$C) -> 0
A8: 1616 | B8: =IFERROR(VLOOKUP(A8, Ingreso!$B:$H, 2, FALSE), "Buscando...") -> Guatero infantil Patito | C8: =IFERROR(VLOOKUP(A8, Ingreso!$B:$H, 7, FALSE), 0) - SUMIF(ventas!$A:$A, A8, ventas!$C:$C) -> 0
A9: 1717 | B9: =IFERROR(VLOOKUP(A9, Ingreso!$B:$H, 2, FALSE), "Buscando...") -> Guatero Infantil Mounstruito | C9: =IFERROR(VLOOKUP(A9, Ingreso!$B:$H, 7, FALSE), 0) - SUMIF(ventas!$A:$A, A9, ventas!$C:$C) -> 4
A10: 808708 | B10: =IFERROR(VLOOKUP(A10, Ingreso!$B:$H, 2, FALSE), "Buscando...") -> Taza Margarita vidrio | C10: =IFERROR(VLOOKUP(A10, Ingreso!$B:$H, 7, FALSE), 0) - SUMIF(ventas!$A:$A, A10, ventas!$C:$C) -> 0
A11: 601873 | B11: =IFERROR(VLOOKUP(A11, Ingreso!$B:$H, 2, FALSE), "Buscando...") -> Burlete Puerta 95cm | C11: =IFERROR(VLOOKUP(A11, Ingreso!$B:$H, 7, FALSE), 0) - SUMIF(ventas!$A:$A, A11, ventas!$C:$C) -> 4
A12: 1313 | B12: =IFERROR(VLOOKUP(A12, Ingreso!$B:$H, 2, FALSE), "Buscando...") -> Organizador Maquillaje y skincare | C12: =IFERROR(VLOOKUP(A12, Ingreso!$B:$H, 7, FALSE), 0) - SUMIF(ventas!$A:$A, A12, ventas!$C:$C) -> 4
A13: 808698 | B13: =IFERROR(VLOOKUP(A13, Ingreso!$B:$H, 2, FALSE), "Buscando...") -> Taza Flores Doble fondo | C13: =IFERROR(VLOOKUP(A13, Ingreso!$B:$H, 7, FALSE), 0) - SUMIF(ventas!$A:$A, A13, ventas!$C:$C) -> 2
A14: 1414 | B14: =IFERROR(VLOOKUP(A14, Ingreso!$B:$H, 2, FALSE), "Buscando...") -> Posavasos bambu 4und | C14: =IFERROR(VLOOKUP(A14, Ingreso!$B:$H, 7, FALSE), 0) - SUMIF(ventas!$A:$A, A14, ventas!$C:$C) -> 4
A15: 655188 | B15: =IFERROR(VLOOKUP(A15, Ingreso!$B:$H, 2, FALSE), "Buscando...") -> Guatero Conejo 500ml | C15: =IFERROR(VLOOKUP(A15, Ingreso!$B:$H, 7, FALSE), 0) - SUMIF(ventas!$A:$A, A15, ventas!$C:$C) -> 4
... A49: 11409 | B49: =IFERROR(VLOOKUP(A49, Ingreso!$B:$H, 2, FALSE), "Buscando...") -> Bolsa lavadora 40x50cm | C49: =IFERROR(VLOOKUP(A49, Ingreso!$B:$H, 7, FALSE), 0) - SUMIF(ventas!$A:$A, A49, ventas!$C:$C) -> 3
A50: XL830L | B50: =IFERROR(VLOOKUP(A50, Ingreso!$B:$H, 2, FALSE), "Buscando...") -> Humidificador electrico USB | C50: =IFERROR(VLOOKUP(A50, Ingreso!$B:$H, 7, FALSE), 0) - SUMIF(ventas!$A:$A, A50, ventas!$C:$C) -> 5
A51: 6265 | B51: =IFERROR(VLOOKUP(A51, Ingreso!$B:$H, 2, FALSE), "Buscando...") -> Dispensador Agua Electrico USB | C51: =IFERROR(VLOOKUP(A51, Ingreso!$B:$H, 7, FALSE), 0) - SUMIF(ventas!$A:$A, A51, ventas!$C:$C) -> 10
A52: XF-69 | B52: =IFERROR(VLOOKUP(A52, Ingreso!$B:$H, 2, FALSE), "Buscando...") -> Masajeador Corporal recargable | C52: =IFERROR(VLOOKUP(A52, Ingreso!$B:$H, 7, FALSE), 0) - SUMIF(ventas!$A:$A, A52, ventas!$C:$C) -> 9
A53: 13465 | B53: =IFERROR(VLOOKUP(A53, Ingreso!$B:$H, 2, FALSE), "Buscando...") -> Masajeador Facial Hielo | C53: =IFERROR(VLOOKUP(A53, Ingreso!$B:$H, 7, FALSE), 0) - SUMIF(ventas!$A:$A, A53, ventas!$C:$C) -> 14
A54: 13935 | B54: =IFERROR(VLOOKUP(A54, Ingreso!$B:$H, 2, FALSE), "Buscando...") -> Espumador de leche electrico | C54: =IFERROR(VLOOKUP(A54, Ingreso!$B:$H, 7, FALSE), 0) - SUMIF(ventas!$A:$A, A54, ventas!$C:$C) -> 3
A55: 13517 | B55: =IFERROR(VLOOKUP(A55, Ingreso!$B:$H, 2, FALSE), "Buscando...") -> Huevera Plastica | C55: =IFERROR(VLOOKUP(A55, Ingreso!$B:$H, 7, FALSE), 0) - SUMIF(ventas!$A:$A, A55, ventas!$C:$C) -> 0
A56: 6242 | B56: =IFERROR(VLOOKUP(A56, Ingreso!$B:$H, 2, FALSE), "Buscando...") -> Caja esencias 12 und 3ml | C56: =IFERROR(VLOOKUP(A56, Ingreso!$B:$H, 7, FALSE), 0) - SUMIF(ventas!$A:$A, A56, ventas!$C:$C) -> 1
A57: 423722 | B57: =IFERROR(VLOOKUP(A57, Ingreso!$B:$H, 2, FALSE), "Buscando...") -> Filtro Piscina Bestway v25 | C57: =IFERROR(VLOOKUP(A57, Ingreso!$B:$H, 7, FALSE), 0) - SUMIF(ventas!$A:$A, A57, ventas!$C:$C) -> 1
A58: 423524 | B58: =IFERROR(VLOOKUP(A58, Ingreso!$B:$H, 2, FALSE), "Buscando...") -> Piscina Inflable Arcoiris 157*46cm | C58: =IFERROR(VLOOKUP(A58, Ingreso!$B:$H, 7, FALSE), 0) - SUMIF(ventas!$A:$A, A58, ventas!$C:$C) -> 5
A59: 571010 | B59: =IFERROR(VLOOKUP(A59, Ingreso!$B:$H, 2, FALSE), "Buscando...") -> Piscina First Fast Set Inflable | C59: =IFERROR(VLOOKUP(A59, Ingreso!$B:$H, 7, FALSE), 0) - SUMIF(ventas!$A:$A, A59, ventas!$C:$C) -> 6
A60: 423395 | B60: =IFERROR(VLOOKUP(A60, Ingreso!$B:$H, 2, FALSE), "Buscando...") -> Sillon Inflable Arcoiris | C60: =IFERROR(VLOOKUP(A60, Ingreso!$B:$H, 7, FALSE), 0) - SUMIF(ventas!$A:$A, A60, ventas!$C:$C) -> 6
A61: MB090347 | B61: =IFERROR(VLOOKUP(A61, Ingreso!$B:$H, 2, FALSE), "Buscando...") -> Set Pinche mas esponjas | C61: =IFERROR(VLOOKUP(A61, Ingreso!$B:$H, 7, FALSE), 0) - SUMIF(ventas!$A:$A, A61, ventas!$C:$C) -> 11
A62: MB058117 | B62: =IFERROR(VLOOKUP(A62, Ingreso!$B:$H, 2, FALSE), "Buscando...") -> Serum vitamina C 50ml | C62: =IFERROR(VLOOKUP(A62, Ingreso!$B:$H, 7, FALSE), 0) - SUMIF(ventas!$A:$A, A62, ventas!$C:$C) -> 11
A63: MB058189 | B63: =IFERROR(VLOOKUP(A63, Ingreso!$B:$H, 2, FALSE), "Buscando...") -> Serum colágeno 50ml | C63: =IFERROR(VLOOKUP(A63, Ingreso!$B:$H, 7, FALSE), 0) - SUMIF(ventas!$A:$A, A63, ventas!$C:$C) -> 12
A64: MB058116 | B64: =IFERROR(VLOOKUP(A64, Ingreso!$B:$H, 2, FALSE), "Buscando...") -> Crema vitamina C 50g | C64: =IFERROR(VLOOKUP(A64, Ingreso!$B:$H, 7, FALSE), 0) - SUMIF(ventas!$A:$A, A64, ventas!$C:$C) -> 11
A65: MB058190 | B65: =IFERROR(VLOOKUP(A65, Ingreso!$B:$H, 2, FALSE), "Buscando...") -> Crema colágeno 50g | C65: =IFERROR(VLOOKUP(A65, Ingreso!$B:$H, 7, FALSE), 0) - SUMIF(ventas!$A:$A, A65, ventas!$C:$C) -> 12
A66: MB090333 | B66: =IFERROR(VLOOKUP(A66, Ingreso!$B:$H, 2, FALSE), "Buscando...") -> Set skincare mas esponjas 6pcs | C66: =IFERROR(VLOOKUP(A66, Ingreso!$B:$H, 7, FALSE), 0) - SUMIF(ventas!$A:$A, A66, ventas!$C:$C) -> 12
A67: 1010 | B67: =IFERROR(VLOOKUP(A67, Ingreso!$B:$H, 2, FALSE), "Buscando...") -> Centrifuga para ensaladas | C67: =IFERROR(VLOOKUP(A67, Ingreso!$B:$H, 7, FALSE), 0) - SUMIF(ventas!$A:$A, A67, ventas!$C:$C) -> 2
A68: 3030 | B68: =IFERROR(VLOOKUP(A68, Ingreso!$B:$H, 2, FALSE), "Buscando...") -> Botella vidrio para aceite 350ml | C68: =IFERROR(VLOOKUP(A68, Ingreso!$B:$H, 7, FALSE), 0) - SUMIF(ventas!$A:$A, A68, ventas!$C:$C) -> 3
A69: 5050 | B69: =IFERROR(VLOOKUP(A69, Ingreso!$B:$H, 2, FALSE), "Buscando...") -> Colador Tela 14cm | C69: =IFERROR(VLOOKUP(A69, Ingreso!$B:$H, 7, FALSE), 0) - SUMIF(ventas!$A:$A, A69, ventas!$C:$C) -> 3
A70: 2020 | B70: =IFERROR(VLOOKUP(A70, Ingreso!$B:$H, 2, FALSE), "Buscando...") -> Lechero 1200ml | C70: =IFERROR(VLOOKUP(A70, Ingreso!$B:$H, 7, FALSE), 0) - SUMIF(ventas!$A:$A, A70, ventas!$C:$C) -> 6
A71: 4040 | B71: =IFERROR(VLOOKUP(A71, Ingreso!$B:$H, 2, FALSE), "Buscando...") -> Balanza Cocina | C71: =IFERROR(VLOOKUP(A71, Ingreso!$B:$H, 7, FALSE), 0) - SUMIF(ventas!$A:$A, A71, ventas!$C:$C) -> 6
A72: 7070 | B72: =IFERROR(VLOOKUP(A72, Ingreso!$B:$H, 2, FALSE), "Buscando...") -> Gramera Digital 10kg | C72: =IFERROR(VLOOKUP(A72, Ingreso!$B:$H, 7, FALSE), 0) - SUMIF(ventas!$A:$A, A72, ventas!$C:$C) -> 6
A73: 6060 | B73: =IFERROR(VLOOKUP(A73, Ingreso!$B:$H, 2, FALSE), "Buscando...") -> Tostador Mango Madera | C73: =IFERROR(VLOOKUP(A73, Ingreso!$B:$H, 7, FALSE), 0) - SUMIF(ventas!$A:$A, A73, ventas!$C:$C) -> 8
A74: 3131 | B74: =IFERROR(VLOOKUP(A74, Ingreso!$B:$H, 2, FALSE), "Buscando...") -> Exprimidor Limon Vidrio | C74: =IFERROR(VLOOKUP(A74, Ingreso!$B:$H, 7, FALSE), 0) - SUMIF(ventas!$A:$A, A74, ventas!$C:$C) -> 9
A75: 826840 | B75: =IFERROR(VLOOKUP(A75, Ingreso!$B:$H, 2, FALSE), "Buscando...") -> Azucarero vidrio relieve | C75: =IFERROR(VLOOKUP(A75, Ingreso!$B:$H, 7, FALSE), 0) - SUMIF(ventas!$A:$A, A75, ventas!$C:$C) -> 4
A76: 39756 | B76: =IFERROR(VLOOKUP(A76, Ingreso!$B:$H, 2, FALSE), "Buscando...") -> Sarten de animalitos | C76: =IFERROR(VLOOKUP(A76, Ingreso!$B:$H, 7, FALSE), 0) - SUMIF(ventas!$A:$A, A76, ventas!$C:$C) -> 3
A77: 61508 | B77: =IFERROR(VLOOKUP(A77, Ingreso!$B:$H, 2, FALSE), "Buscando...") -> Tetera Infusora Vidrio | C77: =IFERROR(VLOOKUP(A77, Ingreso!$B:$H, 7, FALSE), 0) - SUMIF(ventas!$A:$A, A77, ventas!$C:$C) -> 2
A78: 17709-8 | B78: =IFERROR(VLOOKUP(A78, Ingreso!$B:$H, 2, FALSE), "Buscando...") -> Cargador Inalambrico Magsafe | C78: =IFERROR(VLOOKUP(A78, Ingreso!$B:$H, 7, FALSE), 0) - SUMIF(ventas!$A:$A, A78, ventas!$C:$C) -> 3
A79: 52507 | B79: =IFERROR(VLOOKUP(A79, Ingreso!$B:$H, 2, FALSE), "Buscando...") -> Audifonos Airpods Pro 2 | C79: =IFERROR(VLOOKUP(A79, Ingreso!$B:$H, 7, FALSE), 0) - SUMIF(ventas!$A:$A, A79, ventas!$C:$C) -> -1

Sheet ventas
A1: REGISTRO DE VENTAS REALIZADAS
A3: SKU | B3: Producto | C3: Cantidad | D3: Valor Total | E3: Medio de Pago | F3: Costo Unit. | G3: Ganancia Real | H3: Impuesto (19%) | I3: Comisión MP (2.6%)
A4: XL830L | B4: =IF(A4<>"", IFERROR(VLOOKUP(A4, Ingreso!$B:$H, 2, FALSE), "No existe SKU"), "") -> Humidificador electrico USB | C4: 1 | D4: =C4*( VLOOKUP(A4,Ingreso!B:G,6,0)) -> 3890 | E4: Tarjeta | F4: =IF(A4<>"", IFERROR(VLOOKUP(A4, Ingreso!$B:$D, 3, FALSE), 0), "") -> 1900 | G4: =IF(A4<>"", (D4 - (IFERROR(F4,0) * C4)) - H4 - I4, "") -> 1510.76 | H4: =IF(A4<>"", (D4 - (IFERROR(F4,0) * C4)) * 0.19, "") -> 378.1 | I4: =IF(AND(A4<>"", E4="Tarjeta"), D4 * 0.026, 0) -> 101.14
A5: 13465 | B5: =IF(A5<>"", IFERROR(VLOOKUP(A5, Ingreso!$B:$H, 2, FALSE), "No existe SKU"), "") -> Masajeador Facial Hielo | C5: 1 | D5: =C5*( VLOOKUP(A5,Ingreso!B:G,6,0)) -> 1990 | E5: Tarjeta | F5: =IF(A5<>"", IFERROR(VLOOKUP(A5, Ingreso!$B:$D, 3, FALSE), 0), "") -> 1000 | G5: =IF(A5<>"", (D5 - (IFERROR(F5,0) * C5)) - H5 - I5, "") -> 750.16 | H5: =IF(A5<>"", (D5 - (IFERROR(F5,0) * C5)) * 0.19, "") -> 188.1 | I5: =IF(AND(A5<>"", E5="Tarjeta"), D5 * 0.026, 0) -> 51.74
A6: 807597 | B6: =IF(A6<>"", IFERROR(VLOOKUP(A6, Ingreso!$B:$H, 2, FALSE), "No existe SKU"), "") -> Frasco para miel vidrio y bambu | C6: 1 | D6: =C6*( VLOOKUP(A6,Ingreso!B:G,6,0)) -> 5290 | E6: Tarjeta | F6: =IF(A6<>"", IFERROR(VLOOKUP(A6, Ingreso!$B:$D, 3, FALSE), 0), "") -> 2600 | G6: =IF(A6<>"", (D6 - (IFERROR(F6,0) * C6)) - H6 - I6, "") -> 2041.36 | H6: =IF(A6<>"", (D6 - (IFERROR(F6,0) * C6)) * 0.19, "") -> 511.1 | I6: =IF(AND(A6<>"", E6="Tarjeta"), D6 * 0.026, 0) -> 137.54
A7: 22493 | B7: =IF(A7<>"", IFERROR(VLOOKUP(A7, Ingreso!$B:$H, 2, FALSE), "No existe SKU"), "") -> Caja organizadora Te 6 compartimientos 24*17*7cm | C7: 1 | D7: =C7*( VLOOKUP(A7,Ingreso!B:G,6,0)) -> 6990 | E7: Tarjeta | F7: =IF(A7<>"", IFERROR(VLOOKUP(A7, Ingreso!$B:$D, 3, FALSE), 0), "") -> 3500 | G7: =IF(A7<>"", (D7 - (IFERROR(F7,0) * C7)) - H7 - I7, "") -> 2645.16 | H7: =IF(A7<>"", (D7 - (IFERROR(F7,0) * C7)) * 0.19, "") -> 663.1 | I7: =IF(AND(A7<>"", E7="Tarjeta"), D7 * 0.026, 0) -> 181.74
A8: 15154 | B8: =IF(A8<>"", IFERROR(VLOOKUP(A8, Ingreso!$B:$H, 2, FALSE), "No existe SKU"), "") -> tripack paños de cocina | C8: 1 | D8: =C8*( VLOOKUP(A8,Ingreso!B:G,6,0)) -> 4690 | E8: Tarjeta | F8: =IF(A8<>"", IFERROR(VLOOKUP(A8, Ingreso!$B:$D, 3, FALSE), 0), "") -> 2300 | G8: =IF(A8<>"", (D8 - (IFERROR(F8,0) * C8)) - H8 - I8, "") -> 1813.96 | H8: =IF(A8<>"", (D8 - (IFERROR(F8,0) * C8)) * 0.19, "") -> 454.1 | I8: =IF(AND(A8<>"", E8="Tarjeta"), D8 * 0.026, 0) -> 121.94
A9: 6060 | B9: =IF(A9<>"", IFERROR(VLOOKUP(A9, Ingreso!$B:$H, 2, FALSE), "No existe SKU"), "") -> Tostador Mango Madera | C9: 1 | D9: =C9*( VLOOKUP(A9,Ingreso!B:G,6,0)) -> 2990 | E9: Transferencia | F9: =IF(A9<>"", IFERROR(VLOOKUP(A9, Ingreso!$B:$D, 3, FALSE), 0), "") -> 1000 | G9: =IF(A9<>"", (D9 - (IFERROR(F9,0) * C9)) - H9 - I9, "") -> 1611.9 | H9: =IF(A9<>"", (D9 - (IFERROR(F9,0) * C9)) * 0.19, "") -> 378.1 | I9: =IF(AND(A9<>"", E9="Tarjeta"), D9 * 0.026, 0) -> 0
A10: 50948 | B10: =IF(A10<>"", IFERROR(VLOOKUP(A10, Ingreso!$B:$H, 2, FALSE), "No existe SKU"), "") -> Salvamantel Metalico 18*18*1,5cm | C10: 1 | D10: =C10*( VLOOKUP(A10,Ingreso!B:G,6,0)) -> 2690 | E10: Transferencia | F10: =IF(A10<>"", IFERROR(VLOOKUP(A10, Ingreso!$B:$D, 3, FALSE), 0), "") -> 1300 | G10: =IF(A10<>"", (D10 - (IFERROR(F10,0) * C10)) - H10 - I10, "") -> 1125.9 | H10: =IF(A10<>"", (D10 - (IFERROR(F10,0) * C10)) * 0.19, "") -> 264.1 | I10: =IF(AND(A10<>"", E10="Tarjeta"), D10 * 0.026, 0) -> 0
A11: 3131 | B11: =IF(A11<>"", IFERROR(VLOOKUP(A11, Ingreso!$B:$H, 2, FALSE), "No existe SKU"), "") -> Exprimidor Limon Vidrio | C11: 1 | D11: =C11*( VLOOKUP(A11,Ingreso!B:G,6,0)) -> 1990 | E11: Transferencia | F11: =IF(A11<>"", IFERROR(VLOOKUP(A11, Ingreso!$B:$D, 3, FALSE), 0), "") -> 950 | G11: =IF(A11<>"", (D11 - (IFERROR(F11,0) * C11)) - H11 - I11, "") -> 842.4 | H11: =IF(A11<>"", (D11 - (IFERROR(F11,0) * C11)) * 0.19, "") -> 197.6 | I11: =IF(AND(A11<>"", E11="Tarjeta"), D11 * 0.026, 0) -> 0
A12: 23712 | B12: =IF(A12<>"", IFERROR(VLOOKUP(A12, Ingreso!$B:$H, 2, FALSE), "No existe SKU"), "") -> Destapador de botellas Basquetbol 6,5*15*20cm | C12: 1 | D12: =C12*( VLOOKUP(A12,Ingreso!B:G,6,0)) -> 5590 | E12: Transferencia | F12: =IF(A12<>"", IFERROR(VLOOKUP(A12, Ingreso!$B:$D, 3, FALSE), 0), "") -> 2750 | G12: =IF(A12<>"", (D12 - (IFERROR(F12,0) * C12)) - H12 - I12, "") -> 2300.4 | H12: =IF(A12<>"", (D12 - (IFERROR(F12,0) * C12)) * 0.19, "") -> 539.6 | I12: =IF(AND(A12<>"", E12="Tarjeta"), D12 * 0.026, 0) -> 0
A13: 809939 | B13: =IF(A13<>"", IFERROR(VLOOKUP(A13, Ingreso!$B:$H, 2, FALSE), "No existe SKU"), "") -> Set de especies 8und bambu | C13: 1 | D13: =C13*( VLOOKUP(A13,Ingreso!B:G,6,0)) -> 17990 | E13: Transferencia | F13: =IF(A13<>"", IFERROR(VLOOKUP(A13, Ingreso!$B:$D, 3, FALSE), 0), "") -> 9000 | G13: =IF(A13<>"", (D13 - (IFERROR(F13,0) * C13)) - H13 - I13, "") -> 7281.9 | H13: =IF(A13<>"", (D13 - (IFERROR(F13,0) * C13)) * 0.19, "") -> 1708.1 | I13: =IF(AND(A13<>"", E13="Tarjeta"), D13 * 0.026, 0) -> 0
A14: 807597 | B14: =IF(A14<>"", IFERROR(VLOOKUP(A14, Ingreso!$B:$H, 2, FALSE), "No existe SKU"), "") -> Frasco para miel vidrio y bambu | C14: 1 | D14: =C14*( VLOOKUP(A14,Ingreso!B:G,6,0)) -> 5290 | E14: Transferencia | F14: =IF(A14<>"", IFERROR(VLOOKUP(A14, Ingreso!$B:$D, 3, FALSE), 0), "") -> 2600 | G14: =IF(A14<>"", (D14 - (IFERROR(F14,0) * C14)) - H14 - I14, "") -> 2178.9 | H14: =IF(A14<>"", (D14 - (IFERROR(F14,0) * C14)) * 0.19, "") -> 511.1 | I14: =IF(AND(A14<>"", E14="Tarjeta"), D14 * 0.026, 0) -> 0
A15: 807597 | B15: =IF(A15<>"", IFERROR(VLOOKUP(A15, Ingreso!$B:$H, 2, FALSE), "No existe SKU"), "") -> Frasco para miel vidrio y bambu | C15: 1 | D15: =C15*( VLOOKUP(A15,Ingreso!B:G,6,0)) -> 5290 | E15: Efectivo | F15: =IF(A15<>"", IFERROR(VLOOKUP(A15, Ingreso!$B:$D, 3, FALSE), 0), "") -> 2600 | G15: =IF(A15<>"", (D15 - (IFERROR(F15,0) * C15)) - H15 - I15, "") -> 2178.9 | H15: =IF(A15<>"", (D15 - (IFERROR(F15,0) * C15)) * 0.19, "") -> 511.1 | I15: =IF(AND(A15<>"", E15="Tarjeta"), D15 * 0.026, 0) -> 0
A16: 22354 | B16: =IF(A16<>"", IFERROR(VLOOKUP(A16, Ingreso!$B:$H, 2, FALSE), "No existe SKU"), "") -> Colgador para Llaves pajaros dorado 20*20cm | C16: 1 | D16: =C16*( VLOOKUP(A16,Ingreso!B:G,6,0)) -> 3890 | E16: Efectivo | F16: =IF(A16<>"", IFERROR(VLOOKUP(A16, Ingreso!$B:$D, 3, FALSE), 0), "") -> 1900 | G16: =IF(A16<>"", (D16 - (IFERROR(F16,0) * C16)) - H16 - I16, "") -> 1611.9 | H16: =IF(A16<>"", (D16 - (IFERROR(F16,0) * C16)) * 0.19, "") -> 378.1 | I16: =IF(AND(A16<>"", E16="Tarjeta"), D16 * 0.026, 0) -> 0
... A22: 1010 | B22: =IF(A22<>"", IFERROR(VLOOKUP(A22, Ingreso!$B:$H, 2, FALSE), "No existe SKU"), "") -> Centrifuga para ensaladas | C22: 1 | D22: =C22*( VLOOKUP(A22,Ingreso!B:G,6,0)) -> 9690 | E22: Efectivo | F22: =IF(A22<>"", IFERROR(VLOOKUP(A22, Ingreso!$B:$D, 3, FALSE), 0), "") -> 4800 | G22: =IF(A22<>"", (D22 - (IFERROR(F22,0) * C22)) - H22 - I22, "") -> 3960.9 | H22: =IF(A22<>"", (D22 - (IFERROR(F22,0) * C22)) * 0.19, "") -> 929.1 | I22: =IF(AND(A22<>"", E22="Tarjeta"), D22 * 0.026, 0) -> 0
A23: 1010 | B23: =IF(A23<>"", IFERROR(VLOOKUP(A23, Ingreso!$B:$H, 2, FALSE), "No existe SKU"), "") -> Centrifuga para ensaladas | C23: 1 | D23: =C23*( VLOOKUP(A23,Ingreso!B:G,6,0)) -> 9690 | F23: =IF(A23<>"", IFERROR(VLOOKUP(A23, Ingreso!$B:$D, 3, FALSE), 0), "") -> 4800 | G23: =IF(A23<>"", (D23 - (IFERROR(F23,0) * C23)) - H23 - I23, "") -> 3960.9 | H23: =IF(A23<>"", (D23 - (IFERROR(F23,0) * C23)) * 0.19, "") -> 929.1 | I23: =IF(AND(A23<>"", E23="Tarjeta"), D23 * 0.026, 0) -> 0
A24: 19571 | B24: =IF(A24<>"", IFERROR(VLOOKUP(A24, Ingreso!$B:$H, 2, FALSE), "No existe SKU"), "") -> Cesta Ropa Cuadrada café con tapa 42*30*56cm | C24: 1 | D24: =C24*( VLOOKUP(A24,Ingreso!B:G,6,0)) -> 15290 | F24: =IF(A24<>"", IFERROR(VLOOKUP(A24, Ingreso!$B:$D, 3, FALSE), 0), "") -> 7600 | G24: =IF(A24<>"", (D24 - (IFERROR(F24,0) * C24)) - H24 - I24, "") -> 6228.9 | H24: =IF(A24<>"", (D24 - (IFERROR(F24,0) * C24)) * 0.19, "") -> 1461.1 | I24: =IF(AND(A24<>"", E24="Tarjeta"), D24 * 0.026, 0) -> 0
A25: 19571 | B25: =IF(A25<>"", IFERROR(VLOOKUP(A25, Ingreso!$B:$H, 2, FALSE), "No existe SKU"), "") -> Cesta Ropa Cuadrada café con tapa 42*30*56cm | C25: 2 | D25: =C25*( VLOOKUP(A25,Ingreso!B:G,6,0)) -> 30580 | F25: =IF(A25<>"", IFERROR(VLOOKUP(A25, Ingreso!$B:$D, 3, FALSE), 0), "") -> 7600 | G25: =IF(A25<>"", (D25 - (IFERROR(F25,0) * C25)) - H25 - I25, "") -> 12457.8 | H25: =IF(A25<>"", (D25 - (IFERROR(F25,0) * C25)) * 0.19, "") -> 2922.2 | I25: =IF(AND(A25<>"", E25="Tarjeta"), D25 * 0.026, 0) -> 0
A26: 1616 | B26: =IF(A26<>"", IFERROR(VLOOKUP(A26, Ingreso!$B:$H, 2, FALSE), "No existe SKU"), "") -> Guatero infantil Patito | C26: 2 | D26: =C26*( VLOOKUP(A26,Ingreso!B:G,6,0)) -> 9180 | F26: =IF(A26<>"", IFERROR(VLOOKUP(A26, Ingreso!$B:$D, 3, FALSE), 0), "") -> 2800 | G26: =IF(A26<>"", (D26 - (IFERROR(F26,0) * C26)) - H26 - I26, "") -> 2899.8 | H26: =IF(A26<>"", (D26 - (IFERROR(F26,0) * C26)) * 0.19, "") -> 680.2 | I26: =IF(AND(A26<>"", E26="Tarjeta"), D26 * 0.026, 0) -> 0
A27: 25936 | B27: =IF(A27<>"", IFERROR(VLOOKUP(A27, Ingreso!$B:$H, 2, FALSE), "No existe SKU"), "") -> Dispensador Lavalozas 18*12cm | C27: 1 | D27: =C27*( VLOOKUP(A27,Ingreso!B:G,6,0)) -> 7890 | F27: =IF(A27<>"", IFERROR(VLOOKUP(A27, Ingreso!$B:$D, 3, FALSE), 0), "") -> 3900 | G27: =IF(A27<>"", (D27 - (IFERROR(F27,0) * C27)) - H27 - I27, "") -> 3231.9 | H27: =IF(A27<>"", (D27 - (IFERROR(F27,0) * C27)) * 0.19, "") -> 758.1 | I27: =IF(AND(A27<>"", E27="Tarjeta"), D27 * 0.026, 0) -> 0
A28: 25936 | B28: =IF(A28<>"", IFERROR(VLOOKUP(A28, Ingreso!$B:$H, 2, FALSE), "No existe SKU"), "") -> Dispensador Lavalozas 18*12cm | C28: 1 | D28: =C28*( VLOOKUP(A28,Ingreso!B:G,6,0)) -> 7890 | E28: Transferencia | F28: =IF(A28<>"", IFERROR(VLOOKUP(A28, Ingreso!$B:$D, 3, FALSE), 0), "") -> 3900 | G28: =IF(A28<>"", (D28 - (IFERROR(F28,0) * C28)) - H28 - I28, "") -> 3231.9 | H28: =IF(A28<>"", (D28 - (IFERROR(F28,0) * C28)) * 0.19, "") -> 758.1 | I28: =IF(AND(A28<>"", E28="Tarjeta"), D28 * 0.026, 0) -> 0
A29: 15511 | B29: =IF(A29<>"", IFERROR(VLOOKUP(A29, Ingreso!$B:$H, 2, FALSE), "No existe SKU"), "") -> Individual Tejido Grisazulado 38cm | C29: 6 | D29: =C29*( VLOOKUP(A29,Ingreso!B:G,6,0)) -> 10140 | F29: =IF(A29<>"", IFERROR(VLOOKUP(A29, Ingreso!$B:$D, 3, FALSE), 0), "") -> 800 | G29: =IF(A29<>"", (D29 - (IFERROR(F29,0) * C29)) - H29 - I29, "") -> 4325.4 | H29: =IF(A29<>"", (D29 - (IFERROR(F29,0) * C29)) * 0.19, "") -> 1014.6 | I29: =IF(AND(A29<>"", E29="Tarjeta"), D29 * 0.026, 0) -> 0
A30: 50499 | B30: =IF(A30<>"", IFERROR(VLOOKUP(A30, Ingreso!$B:$H, 2, FALSE), "No existe SKU"), "") -> Porta Toalla Nova Metalico Mariposa | C30: 1 | D30: =C30*( VLOOKUP(A30,Ingreso!B:G,6,0)) -> 1490 | F30: =IF(A30<>"", IFERROR(VLOOKUP(A30, Ingreso!$B:$D, 3, FALSE), 0), "") -> 700 | G30: =IF(A30<>"", (D30 - (IFERROR(F30,0) * C30)) - H30 - I30, "") -> 639.9 | H30: =IF(A30<>"", (D30 - (IFERROR(F30,0) * C30)) * 0.19, "") -> 150.1 | I30: =IF(AND(A30<>"", E30="Tarjeta"), D30 * 0.026, 0) -> 0
A31: 50948 | B31: =IF(A31<>"", IFERROR(VLOOKUP(A31, Ingreso!$B:$H, 2, FALSE), "No existe SKU"), "") -> Salvamantel Metalico 18*18*1,5cm | C31: 1 | D31: =C31*( VLOOKUP(A31,Ingreso!B:G,6,0)) -> 2690 | F31: =IF(A31<>"", IFERROR(VLOOKUP(A31, Ingreso!$B:$D, 3, FALSE), 0), "") -> 1300 | G31: =IF(A31<>"", (D31 - (IFERROR(F31,0) * C31)) - H31 - I31, "") -> 1125.9 | H31: =IF(A31<>"", (D31 - (IFERROR(F31,0) * C31)) * 0.19, "") -> 264.1 | I31: =IF(AND(A31<>"", E31="Tarjeta"), D31 * 0.026, 0) -> 0
A32: 21930 | B32: =IF(A32<>"", IFERROR(VLOOKUP(A32, Ingreso!$B:$H, 2, FALSE), "No existe SKU"), "") -> Panera Gris con blanco Tejida 6,5*28cm | C32: 1 | D32: =C32*( VLOOKUP(A32,Ingreso!B:G,6,0)) -> 3690 | F32: =IF(A32<>"", IFERROR(VLOOKUP(A32, Ingreso!$B:$D, 3, FALSE), 0), "") -> 1800 | G32: =IF(A32<>"", (D32 - (IFERROR(F32,0) * C32)) - H32 - I32, "") -> 1530.9 | H32: =IF(A32<>"", (D32 - (IFERROR(F32,0) * C32)) * 0.19, "") -> 359.1 | I32: =IF(AND(A32<>"", E32="Tarjeta"), D32 * 0.026, 0) -> 0
A33: XL830L | B33: =IF(A33<>"", IFERROR(VLOOKUP(A33, Ingreso!$B:$H, 2, FALSE), "No existe SKU"), "") -> Humidificador electrico USB | C33: 1 | D33: =C33*( VLOOKUP(A33,Ingreso!B:G,6,0)) -> 3890 | E33: Tarjeta | F33: =IF(A33<>"", IFERROR(VLOOKUP(A33, Ingreso!$B:$D, 3, FALSE), 0), "") -> 1900 | G33: =IF(A33<>"", (D33 - (IFERROR(F33,0) * C33)) - H33 - I33, "") -> 1510.76 | H33: =IF(A33<>"", (D33 - (IFERROR(F33,0) * C33)) * 0.19, "") -> 378.1 | I33: =IF(AND(A33<>"", E33="Tarjeta"), D33 * 0.026, 0) -> 101.14
A34: 601873 | B34: =IF(A34<>"", IFERROR(VLOOKUP(A34, Ingreso!$B:$H, 2, FALSE), "No existe SKU"), "") -> Burlete Puerta 95cm | C34: 1 | D34: =C34*( VLOOKUP(A34,Ingreso!B:G,6,0)) -> 2490 | E34: Tarjeta | F34: =IF(A34<>"", IFERROR(VLOOKUP(A34, Ingreso!$B:$D, 3, FALSE), 0), "") -> 1000 | G34: =IF(A34<>"", (D34 - (IFERROR(F34,0) * C34)) - H34 - I34, "") -> 1142.16 | H34: =IF(A34<>"", (D34 - (IFERROR(F34,0) * C34)) * 0.19, "") -> 283.1 | I34: =IF(AND(A34<>"", E34="Tarjeta"), D34 * 0.026, 0) -> 64.74
A35: 1717 | B35: =IF(A35<>"", IFERROR(VLOOKUP(A35, Ingreso!$B:$H, 2, FALSE), "No existe SKU"), "") -> Guatero Infantil Mounstruito | C35: 1 | D35: =C35*( VLOOKUP(A35,Ingreso!B:G,6,0)) -> 4590 | E35: Tarjeta | F35: =IF(A35<>"", IFERROR(VLOOKUP(A35, Ingreso!$B:$D, 3, FALSE), 0), "") -> 2000 | G35: =IF(A35<>"", (D35 - (IFERROR(F35,0) * C35)) - H35 - I35, "") -> 1978.56 | H35: =IF(A35<>"", (D35 - (IFERROR(F35,0) * C35)) * 0.19, "") -> 492.1 | I35: =IF(AND(A35<>"", E35="Tarjeta"), D35 * 0.026, 0) -> 119.34
A36: 15154 | B36: =IF(A36<>"", IFERROR(VLOOKUP(A36, Ingreso!$B:$H, 2, FALSE), "No existe SKU"), "") -> tripack paños de cocina | C36: 1 | D36: =C36*( VLOOKUP(A36,Ingreso!B:G,6,0)) -> 4690 | E36: Tarjeta | F36: =IF(A36<>"", IFERROR(VLOOKUP(A36, Ingreso!$B:$D, 3, FALSE), 0), "") -> 2300 | G36: =IF(A36<>"", (D36 - (IFERROR(F36,0) * C36)) - H36 - I36, "") -> 1813.96 | H36: =IF(A36<>"", (D36 - (IFERROR(F36,0) * C36)) * 0.19, "") -> 454.1 | I36: =IF(AND(A36<>"", E36="Tarjeta"), D36 * 0.026, 0) -> 121.94
A37: 50499 | B37: =IF(A37<>"", IFERROR(VLOOKUP(A37, Ingreso!$B:$H, 2, FALSE), "No existe SKU"), "") -> Porta Toalla Nova Metalico Mariposa | C37: 1 | D37: =C37*( VLOOKUP(A37,Ingreso!B:G,6,0)) -> 1490 | E37: Tarjeta | F37: =IF(A37<>"", IFERROR(VLOOKUP(A37, Ingreso!$B:$D, 3, FALSE), 0), "") -> 700 | G37: =IF(A37<>"", (D37 - (IFERROR(F37,0) * C37)) - H37 - I37, "") -> 601.16 | H37: =IF(A37<>"", (D37 - (IFERROR(F37,0) * C37)) * 0.19, "") -> 150.1 | I37: =IF(AND(A37<>"", E37="Tarjeta"), D37 * 0.026, 0) -> 38.74
A38: 807597 | B38: =IF(A38<>"", IFERROR(VLOOKUP(A38, Ingreso!$B:$H, 2, FALSE), "No existe SKU"), "") -> Frasco para miel vidrio y bambu | C38: 1 | D38: =C38*( VLOOKUP(A38,Ingreso!B:G,6,0)) -> 5290 | F38: =IF(A38<>"", IFERROR(VLOOKUP(A38, Ingreso!$B:$D, 3, FALSE), 0), "") -> 2600 | G38: =IF(A38<>"", (D38 - (IFERROR(F38,0) * C38)) - H38 - I38, "") -> 2178.9 | H38: =IF(A38<>"", (D38 - (IFERROR(F38,0) * C38)) * 0.19, "") -> 511.1 | I38: =IF(AND(A38<>"", E38="Tarjeta"), D38 * 0.026, 0) -> 0
A39: 19571 | B39: =IF(A39<>"", IFERROR(VLOOKUP(A39, Ingreso!$B:$H, 2, FALSE), "No existe SKU"), "") -> Cesta Ropa Cuadrada café con tapa 42*30*56cm | C39: 1 | D39: =C39*( VLOOKUP(A39,Ingreso!B:G,6,0)) -> 15290 | F39: =IF(A39<>"", IFERROR(VLOOKUP(A39, Ingreso!$B:$D, 3, FALSE), 0), "") -> 7600 | G39: =IF(A39<>"", (D39 - (IFERROR(F39,0) * C39)) - H39 - I39, "") -> 6228.9 | H39: =IF(A39<>"", (D39 - (IFERROR(F39,0) * C39)) * 0.19, "") -> 1461.1 | I39: =IF(AND(A39<>"", E39="Tarjeta"), D39 * 0.026, 0) -> 0
A40: 51248 | B40: =IF(A40<>"", IFERROR(VLOOKUP(A40, Ingreso!$B:$H, 2, FALSE), "No existe SKU"), "") -> Cesta con cierre algodon 41*32*53cm | C40: 1 | D40: =C40*( VLOOKUP(A40,Ingreso!B:G,6,0)) -> 6390 | E40: Transferencia | F40: =IF(A40<>"", IFERROR(VLOOKUP(A40, Ingreso!$B:$D, 3, FALSE), 0), "") -> 3150 | G40: =IF(A40<>"", (D40 - (IFERROR(F40,0) * C40)) - H40 - I40, "") -> 2624.4 | H40: =IF(A40<>"", (D40 - (IFERROR(F40,0) * C40)) * 0.19, "") -> 615.6 | I40: =IF(AND(A40<>"", E40="Tarjeta"), D40 * 0.026, 0) -> 0
A41: 24217 | B41: =IF(A41<>"", IFERROR(VLOOKUP(A41, Ingreso!$B:$H, 2, FALSE), "No existe SKU"), "") -> Cesta Ropa Dinosaurio 40*50cm | C41: 1 | D41: =C41*( VLOOKUP(A41,Ingreso!B:G,6,0)) -> 5490 | E41: Transferencia | F41: =IF(A41<>"", IFERROR(VLOOKUP(A41, Ingreso!$B:$D, 3, FALSE), 0), "") -> 2550 | G41: =IF(A41<>"", (D41 - (IFERROR(F41,0) * C41)) - H41 - I41, "") -> 2381.4 | H41: =IF(A41<>"", (D41 - (IFERROR(F41,0) * C41)) * 0.19, "") -> 558.6 | I41: =IF(AND(A41<>"", E41="Tarjeta"), D41 * 0.026, 0) -> 0
A42: 50948 | B42: =IF(A42<>"", IFERROR(VLOOKUP(A42, Ingreso!$B:$H, 2, FALSE), "No existe SKU"), "") -> Salvamantel Metalico 18*18*1,5cm | C42: 1 | D42: =C42*( VLOOKUP(A42,Ingreso!B:G,6,0)) -> 2690 | E42: Transferencia | F42: =IF(A42<>"", IFERROR(VLOOKUP(A42, Ingreso!$B:$D, 3, FALSE), 0), "") -> 1300 | G42: =IF(A42<>"", (D42 - (IFERROR(F42,0) * C42)) - H42 - I42, "") -> 1125.9 | H42: =IF(A42<>"", (D42 - (IFERROR(F42,0) * C42)) * 0.19, "") -> 264.1 | I42: =IF(AND(A42<>"", E42="Tarjeta"), D42 * 0.026, 0) -> 0
A43: 808708 | B43: =IF(A43<>"", IFERROR(VLOOKUP(A43, Ingreso!$B:$H, 2, FALSE), "No existe SKU"), "") -> Taza Margarita vidrio | C43: 1 | D43: =C43*( VLOOKUP(A43,Ingreso!B:G,6,0)) -> 3990 | E43: Transferencia | F43: =IF(A43<>"", IFERROR(VLOOKUP(A43, Ingreso!$B:$D, 3, FALSE), 0), "") -> 2000 | G43: =IF(A43<>"", (D43 - (IFERROR(F43,0) * C43)) - H43 - I43, "") -> 1611.9 | H43: =IF(A43<>"", (D43 - (IFERROR(F43,0) * C43)) * 0.19, "") -> 378.1 | I43: =IF(AND(A43<>"", E43="Tarjeta"), D43 * 0.026, 0) -> 0
A44: 2020 | B44: =IF(A44<>"", IFERROR(VLOOKUP(A44, Ingreso!$B:$H, 2, FALSE), "No existe SKU"), "") -> Lechero 1200ml | C44: 1 | D44: =C44*( VLOOKUP(A44,Ingreso!B:G,6,0)) -> 3990 | F44: =IF(A44<>"", IFERROR(VLOOKUP(A44, Ingreso!$B:$D, 3, FALSE), 0), "") -> 2000 | G44: =IF(A44<>"", (D44 - (IFERROR(F44,0) * C44)) - H44 - I44, "") -> 1611.9 | H44: =IF(A44<>"", (D44 - (IFERROR(F44,0) * C44)) * 0.19, "") -> 378.1 | I44: =IF(AND(A44<>"", E44="Tarjeta"), D44 * 0.026, 0) -> 0
A45: 6060 | B45: =IF(A45<>"", IFERROR(VLOOKUP(A45, Ingreso!$B:$H, 2, FALSE), "No existe SKU"), "") -> Tostador Mango Madera | C45: 1 | D45: =C45*( VLOOKUP(A45,Ingreso!B:G,6,0)) -> 2990 | F45: =IF(A45<>"", IFERROR(VLOOKUP(A45, Ingreso!$B:$D, 3, FALSE), 0), "") -> 1000 | G45: =IF(A45<>"", (D45 - (IFERROR(F45,0) * C45)) - H45 - I45, "") -> 1611.9 | H45: =IF(A45<>"", (D45 - (IFERROR(F45,0) * C45)) * 0.19, "") -> 378.1 | I45: =IF(AND(A45<>"", E45="Tarjeta"), D45 * 0.026, 0) -> 0
A46: 808708 | B46: =IF(A46<>"", IFERROR(VLOOKUP(A46, Ingreso!$B:$H, 2, FALSE), "No existe SKU"), "") -> Taza Margarita vidrio | C46: 1 | D46: =C46*( VLOOKUP(A46,Ingreso!B:G,6,0)) -> 3990 | F46: =IF(A46<>"", IFERROR(VLOOKUP(A46, Ingreso!$B:$D, 3, FALSE), 0), "") -> 2000 | G46: =IF(A46<>"", (D46 - (IFERROR(F46,0) * C46)) - H46 - I46, "") -> 1611.9 | H46: =IF(A46<>"", (D46 - (IFERROR(F46,0) * C46)) * 0.19, "") -> 378.1 | I46: =IF(AND(A46<>"", E46="Tarjeta"), D46 * 0.026, 0) -> 0
A47: 809939 | B47: =IF(A47<>"", IFERROR(VLOOKUP(A47, Ingreso!$B:$H, 2, FALSE), "No existe SKU"), "") -> Set de especies 8und bambu | C47: 1 | D47: =C47*( VLOOKUP(A47,Ingreso!B:G,6,0)) -> 17990 | F47: =IF(A47<>"", IFERROR(VLOOKUP(A47, Ingreso!$B:$D, 3, FALSE), 0), "") -> 9000 | G47: =IF(A47<>"", (D47 - (IFERROR(F47,0) * C47)) - H47 - I47, "") -> 7281.9 | H47: =IF(A47<>"", (D47 - (IFERROR(F47,0) * C47)) * 0.19, "") -> 1708.1 | I47: =IF(AND(A47<>"", E47="Tarjeta"), D47 * 0.026, 0) -> 0
A48: 21455 | B48: =IF(A48<>"", IFERROR(VLOOKUP(A48, Ingreso!$B:$H, 2, FALSE), "No existe SKU"), "") -> Zapatero Negro Plastico Varillas Metalicas 4 pisos 41*18,5*50cm | C48: 1 | D48: =C48*( VLOOKUP(A48,Ingreso!B:G,6,0)) -> 4990 | E48: Tarjeta | F48: =IF(A48<>"", IFERROR(VLOOKUP(A48, Ingreso!$B:$D, 3, FALSE), 0), "") -> 1800 | G48: =IF(A48<>"", (D48 - (IFERROR(F48,0) * C48)) - H48 - I48, "") -> 2454.16 | H48: =IF(A48<>"", (D48 - (IFERROR(F48,0) * C48)) * 0.19, "") -> 606.1 | I48: =IF(AND(A48<>"", E48="Tarjeta"), D48 * 0.026, 0) -> 129.74
A49: 15855 | B49: =IF(A49<>"", IFERROR(VLOOKUP(A49, Ingreso!$B:$H, 2, FALSE), "No existe SKU"), "") -> Frutero Metalico 27*10cm | C49: 1 | D49: =C49*( VLOOKUP(A49,Ingreso!B:G,6,0)) -> 3990 | E49: Tarjeta | F49: =IF(A49<>"", IFERROR(VLOOKUP(A49, Ingreso!$B:$D, 3, FALSE), 0), "") -> 2000 | G49: =IF(A49<>"", (D49 - (IFERROR(F49,0) * C49)) - H49 - I49, "") -> 1508.16 | H49: =IF(A49<>"", (D49 - (IFERROR(F49,0) * C49)) * 0.19, "") -> 378.1 | I49: =IF(AND(A49<>"", E49="Tarjeta"), D49 * 0.026, 0) -> 103.74
A50: 15154 | B50: =IF(A50<>"", IFERROR(VLOOKUP(A50, Ingreso!$B:$H, 2, FALSE), "No existe SKU"), "") -> tripack paños de cocina | C50: 1 | D50: =C50*( VLOOKUP(A50,Ingreso!B:G,6,0)) -> 4690 | E50: Tarjeta | F50: =IF(A50<>"", IFERROR(VLOOKUP(A50, Ingreso!$B:$D, 3, FALSE), 0), "") -> 2300 | G50: =IF(A50<>"", (D50 - (IFERROR(F50,0) * C50)) - H50 - I50, "") -> 1813.96 | H50: =IF(A50<>"", (D50 - (IFERROR(F50,0) * C50)) * 0.19, "") -> 454.1 | I50: =IF(AND(A50<>"", E50="Tarjeta"), D50 * 0.026, 0) -> 121.94
A51: 25936 | B51: =IF(A51<>"", IFERROR(VLOOKUP(A51, Ingreso!$B:$H, 2, FALSE), "No existe SKU"), "") -> Dispensador Lavalozas 18*12cm | C51: 1 | D51: =C51*( VLOOKUP(A51,Ingreso!B:G,6,0)) -> 7890 | E51: Tarjeta | F51: =IF(A51<>"", IFERROR(VLOOKUP(A51, Ingreso!$B:$D, 3, FALSE), 0), "") -> 3900 | G51: =IF(A51<>"", (D51 - (IFERROR(F51,0) * C51)) - H51 - I51, "") -> 3026.76 | H51: =IF(A51<>"", (D51 - (IFERROR(F51,0) * C51)) * 0.19, "") -> 758.1 | I51: =IF(AND(A51<>"", E51="Tarjeta"), D51 * 0.026, 0) -> 205.14
A52: 601873 | B52: =IF(A52<>"", IFERROR(VLOOKUP(A52, Ingreso!$B:$H, 2, FALSE), "No existe SKU"), "") -> Burlete Puerta 95cm | C52: 1 | D52: =C52*( VLOOKUP(A52,Ingreso!B:G,6,0)) -> 2490 | E52: Tarjeta | F52: =IF(A52<>"", IFERROR(VLOOKUP(A52, Ingreso!$B:$D, 3, FALSE), 0), "") -> 1000 | G52: =IF(A52<>"", (D52 - (IFERROR(F52,0) * C52)) - H52 - I52, "") -> 1142.16 | H52: =IF(A52<>"", (D52 - (IFERROR(F52,0) * C52)) * 0.19, "") -> 283.1 | I52: =IF(AND(A52<>"", E52="Tarjeta"), D52 * 0.026, 0) -> 64.74
A53: 1717 | B53: =IF(A53<>"", IFERROR(VLOOKUP(A53, Ingreso!$B:$H, 2, FALSE), "No existe SKU"), "") -> Guatero Infantil Mounstruito | C53: 1 | D53: =C53*( VLOOKUP(A53,Ingreso!B:G,6,0)) -> 4590 | E53: Tarjeta | F53: =IF(A53<>"", IFERROR(VLOOKUP(A53, Ingreso!$B:$D, 3, FALSE), 0), "") -> 2000 | G53: =IF(A53<>"", (D53 - (IFERROR(F53,0) * C53)) - H53 - I53, "") -> 1978.56 | H53: =IF(A53<>"", (D53 - (IFERROR(F53,0) * C53)) * 0.19, "") -> 492.1 | I53: =IF(AND(A53<>"", E53="Tarjeta"), D53 * 0.026, 0) -> 119.34
A54: MB090347 | B54: =IF(A54<>"", IFERROR(VLOOKUP(A54, Ingreso!$B:$H, 2, FALSE), "No existe SKU"), "") -> Set Pinche mas esponjas | C54: 1 | D54: =C54*( VLOOKUP(A54,Ingreso!B:G,6,0)) -> 2490 | E54: Tarjeta | F54: =IF(A54<>"", IFERROR(VLOOKUP(A54, Ingreso!$B:$D, 3, FALSE), 0), "") -> 1200 | G54: =IF(A54<>"", (D54 - (IFERROR(F54,0) * C54)) - H54 - I54, "") -> 980.16 | H54: =IF(A54<>"", (D54 - (IFERROR(F54,0) * C54)) * 0.19, "") -> 245.1 | I54: =IF(AND(A54<>"", E54="Tarjeta"), D54 * 0.026, 0) -> 64.74
A55: 21930 | B55: =IF(A55<>"", IFERROR(VLOOKUP(A55, Ingreso!$B:$H, 2, FALSE), "No existe SKU"), "") -> Panera Gris con blanco Tejida 6,5*28cm | C55: 1 | D55: =C55*( VLOOKUP(A55,Ingreso!B:G,6,0)) -> 3690 | E55: Tarjeta | F55: =IF(A55<>"", IFERROR(VLOOKUP(A55, Ingreso!$B:$D, 3, FALSE), 0), "") -> 1800 | G55: =IF(A55<>"", (D55 - (IFERROR(F55,0) * C55)) - H55 - I55, "") -> 1434.96 | H55: =IF(A55<>"", (D55 - (IFERROR(F55,0) * C55)) * 0.19, "") -> 359.1 | I55: =IF(AND(A55<>"", E55="Tarjeta"), D55 * 0.026, 0) -> 95.94
A56: 1717 | B56: =IF(A56<>"", IFERROR(VLOOKUP(A56, Ingreso!$B:$H, 2, FALSE), "No existe SKU"), "") -> Guatero Infantil Mounstruito | C56: 1 | D56: =C56*( VLOOKUP(A56,Ingreso!B:G,6,0)) -> 4590 | E56: Tarjeta | F56: =IF(A56<>"", IFERROR(VLOOKUP(A56, Ingreso!$B:$D, 3, FALSE), 0), "") -> 2000 | G56: =IF(A56<>"", (D56 - (IFERROR(F56,0) * C56)) - H56 - I56, "") -> 1978.56 | H56: =IF(A56<>"", (D56 - (IFERROR(F56,0) * C56)) * 0.19, "") -> 492.1 | I56: =IF(AND(A56<>"", E56="Tarjeta"), D56 * 0.026, 0) -> 119.34
A57: 15154 | B57: =IF(A57<>"", IFERROR(VLOOKUP(A57, Ingreso!$B:$H, 2, FALSE), "No existe SKU"), "") -> tripack paños de cocina | C57: 1 | D57: =C57*( VLOOKUP(A57,Ingreso!B:G,6,0)) -> 4690 | E57: Tarjeta | F57: =IF(A57<>"", IFERROR(VLOOKUP(A57, Ingreso!$B:$D, 3, FALSE), 0), "") -> 2300 | G57: =IF(A57<>"", (D57 - (IFERROR(F57,0) * C57)) - H57 - I57, "") -> 1813.96 | H57: =IF(A57<>"", (D57 - (IFERROR(F57,0) * C57)) * 0.19, "") -> 454.1 | I57: =IF(AND(A57<>"", E57="Tarjeta"), D57 * 0.026, 0) -> 121.94
A58: 2020 | B58: =IF(A58<>"", IFERROR(VLOOKUP(A58, Ingreso!$B:$H, 2, FALSE), "No existe SKU"), "") -> Lechero 1200ml | C58: 1 | D58: =C58*( VLOOKUP(A58,Ingreso!B:G,6,0)) -> 3990 | E58: Tarjeta | F58: =IF(A58<>"", IFERROR(VLOOKUP(A58, Ingreso!$B:$D, 3, FALSE), 0), "") -> 2000 | G58: =IF(A58<>"", (D58 - (IFERROR(F58,0) * C58)) - H58 - I58, "") -> 1508.16 | H58: =IF(A58<>"", (D58 - (IFERROR(F58,0) * C58)) * 0.19, "") -> 378.1 | I58: =IF(AND(A58<>"", E58="Tarjeta"), D58 * 0.026, 0) -> 103.74
A59: XL830L | B59: =IF(A59<>"", IFERROR(VLOOKUP(A59, Ingreso!$B:$H, 2, FALSE), "No existe SKU"), "") -> Humidificador electrico USB | C59: 1 | D59: =C59*( VLOOKUP(A59,Ingreso!B:G,6,0)) -> 3890 | E59: Tarjeta | F59: =IF(A59<>"", IFERROR(VLOOKUP(A59, Ingreso!$B:$D, 3, FALSE), 0), "") -> 1900 | G59: =IF(A59<>"", (D59 - (IFERROR(F59,0) * C59)) - H59 - I59, "") -> 1510.76 | H59: =IF(A59<>"", (D59 - (IFERROR(F59,0) * C59)) * 0.19, "") -> 378.1 | I59: =IF(AND(A59<>"", E59="Tarjeta"), D59 * 0.026, 0) -> 101.14
A60: 1010 | B60: =IF(A60<>"", IFERROR(VLOOKUP(A60, Ingreso!$B:$H, 2, FALSE), "No existe SKU"), "") -> Centrifuga para ensaladas | C60: 1 | D60: =C60*( VLOOKUP(A60,Ingreso!B:G,6,0)) -> 9690 | E60: Tarjeta | F60: =IF(A60<>"", IFERROR(VLOOKUP(A60, Ingreso!$B:$D, 3, FALSE), 0), "") -> 4800 | G60: =IF(A60<>"", (D60 - (IFERROR(F60,0) * C60)) - H60 - I60, "") -> 3708.96 | H60: =IF(A60<>"", (D60 - (IFERROR(F60,0) * C60)) * 0.19, "") -> 929.1 | I60: =IF(AND(A60<>"", E60="Tarjeta"), D60 * 0.026, 0) -> 251.94
A61: 3131 | B61: =IF(A61<>"", IFERROR(VLOOKUP(A61, Ingreso!$B:$H, 2, FALSE), "No existe SKU"), "") -> Exprimidor Limon Vidrio | C61: 1 | D61: =C61*( VLOOKUP(A61,Ingreso!B:G,6,0)) -> 1990 | E61: Tarjeta | F61: =IF(A61<>"", IFERROR(VLOOKUP(A61, Ingreso!$B:$D, 3, FALSE), 0), "") -> 950 | G61: =IF(A61<>"", (D61 - (IFERROR(F61,0) * C61)) - H61 - I61, "") -> 790.66 | H61: =IF(A61<>"", (D61 - (IFERROR(F61,0) * C61)) * 0.19, "") -> 197.6 | I61: =IF(AND(A61<>"", E61="Tarjeta"), D61 * 0.026, 0) -> 51.74
A62: 1515 | B62: =IF(A62<>"", IFERROR(VLOOKUP(A62, Ingreso!$B:$H, 2, FALSE), "No existe SKU"), "") -> Salero y Pimentero Pareja | C62: 1 | D62: =C62*( VLOOKUP(A62,Ingreso!B:G,6,0)) -> 4990 | E62: Tarjeta | F62: =IF(A62<>"", IFERROR(VLOOKUP(A62, Ingreso!$B:$D, 3, FALSE), 0), "") -> 2500 | G62: =IF(A62<>"", (D62 - (IFERROR(F62,0) * C62)) - H62 - I62, "") -> 1887.16 | H62: =IF(A62<>"", (D62 - (IFERROR(F62,0) * C62)) * 0.19, "") -> 473.1 | I62: =IF(AND(A62<>"", E62="Tarjeta"), D62 * 0.026, 0) -> 129.74
A63: 22489 | B63: =IF(A63<>"", IFERROR(VLOOKUP(A63, Ingreso!$B:$H, 2, FALSE), "No existe SKU"), "") -> Caja organizadora Te 4 compartimiento15*15*7cm | C63: 1 | D63: =C63*( VLOOKUP(A63,Ingreso!B:G,6,0)) -> 6290 | E63: Tarjeta | F63: =IF(A63<>"", IFERROR(VLOOKUP(A63, Ingreso!$B:$D, 3, FALSE), 0), "") -> 3100 | G63: =IF(A63<>"", (D63 - (IFERROR(F63,0) * C63)) - H63 - I63, "") -> 2420.36 | H63: =IF(A63<>"", (D63 - (IFERROR(F63,0) * C63)) * 0.19, "") -> 606.1 | I63: =IF(AND(A63<>"", E63="Tarjeta"), D63 * 0.026, 0) -> 163.54
A64: 50948 | B64: =IF(A64<>"", IFERROR(VLOOKUP(A64, Ingreso!$B:$H, 2, FALSE), "No existe SKU"), "") -> Salvamantel Metalico 18*18*1,5cm | C64: 1 | D64: =C64*( VLOOKUP(A64,Ingreso!B:G,6,0)) -> 2690 | E64: Tarjeta | F64: =IF(A64<>"", IFERROR(VLOOKUP(A64, Ingreso!$B:$D, 3, FALSE), 0), "") -> 1300 | G64: =IF(A64<>"", (D64 - (IFERROR(F64,0) * C64)) - H64 - I64, "") -> 1055.96 | H64: =IF(A64<>"", (D64 - (IFERROR(F64,0) * C64)) * 0.19, "") -> 264.1 | I64: =IF(AND(A64<>"", E64="Tarjeta"), D64 * 0.026, 0) -> 69.94
A65: 16922 | B65: =IF(A65<>"", IFERROR(VLOOKUP(A65, Ingreso!$B:$H, 2, FALSE), "No existe SKU"), "") -> Cesta Ropa Diseño Estampado 35*45cm | C65: 1 | D65: =C65*( VLOOKUP(A65,Ingreso!B:G,6,0)) -> 5990 | E65: Tarjeta | F65: =IF(A65<>"", IFERROR(VLOOKUP(A65, Ingreso!$B:$D, 3, FALSE), 0), "") -> 2950 | G65: =IF(A65<>"", (D65 - (IFERROR(F65,0) * C65)) - H65 - I65, "") -> 2306.66 | H65: =IF(A65<>"", (D65 - (IFERROR(F65,0) * C65)) * 0.19, "") -> 577.6 | I65: =IF(AND(A65<>"", E65="Tarjeta"), D65 * 0.026, 0) -> 155.74
A66: 807597 | B66: =IF(A66<>"", IFERROR(VLOOKUP(A66, Ingreso!$B:$H, 2, FALSE), "No existe SKU"), "") -> Frasco para miel vidrio y bambu | C66: 1 | D66: =C66*( VLOOKUP(A66,Ingreso!B:G,6,0)) -> 5290 | E66: Tarjeta | F66: =IF(A66<>"", IFERROR(VLOOKUP(A66, Ingreso!$B:$D, 3, FALSE), 0), "") -> 2600 | G66: =IF(A66<>"", (D66 - (IFERROR(F66,0) * C66)) - H66 - I66, "") -> 2041.36 | H66: =IF(A66<>"", (D66 - (IFERROR(F66,0) * C66)) * 0.19, "") -> 511.1 | I66: =IF(AND(A66<>"", E66="Tarjeta"), D66 * 0.026, 0) -> 137.54
A67: 808708 | B67: =IF(A67<>"", IFERROR(VLOOKUP(A67, Ingreso!$B:$H, 2, FALSE), "No existe SKU"), "") -> Taza Margarita vidrio | C67: 1 | D67: =C67*( VLOOKUP(A67,Ingreso!B:G,6,0)) -> 3990 | F67: =IF(A67<>"", IFERROR(VLOOKUP(A67, Ingreso!$B:$D, 3, FALSE), 0), "") -> 2000 | G67: =IF(A67<>"", (D67 - (IFERROR(F67,0) * C67)) - H67 - I67, "") -> 1611.9 | H67: =IF(A67<>"", (D67 - (IFERROR(F67,0) * C67)) * 0.19, "") -> 378.1 | I67: =IF(AND(A67<>"", E67="Tarjeta"), D67 * 0.026, 0) -> 0
A68: 1515 | B68: =IF(A68<>"", IFERROR(VLOOKUP(A68, Ingreso!$B:$H, 2, FALSE), "No existe SKU"), "") -> Salero y Pimentero Pareja | C68: 1 | D68: =C68*( VLOOKUP(A68,Ingreso!B:G,6,0)) -> 4990 | F68: =IF(A68<>"", IFERROR(VLOOKUP(A68, Ingreso!$B:$D, 3, FALSE), 0), "") -> 2500 | G68: =IF(A68<>"", (D68 - (IFERROR(F68,0) * C68)) - H68 - I68, "") -> 2016.9 | H68: =IF(A68<>"", (D68 - (IFERROR(F68,0) * C68)) * 0.19, "") -> 473.1 | I68: =IF(AND(A68<>"", E68="Tarjeta"), D68 * 0.026, 0) -> 0
A69: XL830L | B69: =IF(A69<>"", IFERROR(VLOOKUP(A69, Ingreso!$B:$H, 2, FALSE), "No existe SKU"), "") -> Humidificador electrico USB | C69: 2 | D69: =C69*( VLOOKUP(A69,Ingreso!B:G,6,0)) -> 7780 | F69: =IF(A69<>"", IFERROR(VLOOKUP(A69, Ingreso!$B:$D, 3, FALSE), 0), "") -> 1900 | G69: =IF(A69<>"", (D69 - (IFERROR(F69,0) * C69)) - H69 - I69, "") -> 3223.8 | H69: =IF(A69<>"", (D69 - (IFERROR(F69,0) * C69)) * 0.19, "") -> 756.2 | I69: =IF(AND(A69<>"", E69="Tarjeta"), D69 * 0.026, 0) -> 0
A70: 808708 | B70: =IF(A70<>"", IFERROR(VLOOKUP(A70, Ingreso!$B:$H, 2, FALSE), "No existe SKU"), "") -> Taza Margarita vidrio | C70: 2 | D70: =C70*( VLOOKUP(A70,Ingreso!B:G,6,0)) -> 7980 | F70: =IF(A70<>"", IFERROR(VLOOKUP(A70, Ingreso!$B:$D, 3, FALSE), 0), "") -> 2000 | G70: =IF(A70<>"", (D70 - (IFERROR(F70,0) * C70)) - H70 - I70, "") -> 3223.8 | H70: =IF(A70<>"", (D70 - (IFERROR(F70,0) * C70)) * 0.19, "") -> 756.2 | I70: =IF(AND(A70<>"", E70="Tarjeta"), D70 * 0.026, 0) -> 0
A71: 808698 | B71: =IF(A71<>"", IFERROR(VLOOKUP(A71, Ingreso!$B:$H, 2, FALSE), "No existe SKU"), "") -> Taza Flores Doble fondo | C71: 2 | D71: =C71*( VLOOKUP(A71,Ingreso!B:G,6,0)) -> 9980 | F71: =IF(A71<>"", IFERROR(VLOOKUP(A71, Ingreso!$B:$D, 3, FALSE), 0), "") -> 2500 | G71: =IF(A71<>"", (D71 - (IFERROR(F71,0) * C71)) - H71 - I71, "") -> 4033.8 | H71: =IF(A71<>"", (D71 - (IFERROR(F71,0) * C71)) * 0.19, "") -> 946.2 | I71: =IF(AND(A71<>"", E71="Tarjeta"), D71 * 0.026, 0) -> 0
A72: 50948 | B72: =IF(A72<>"", IFERROR(VLOOKUP(A72, Ingreso!$B:$H, 2, FALSE), "No existe SKU"), "") -> Salvamantel Metalico 18*18*1,5cm | C72: 1 | D72: =C72*( VLOOKUP(A72,Ingreso!B:G,6,0)) -> 2690 | F72: =IF(A72<>"", IFERROR(VLOOKUP(A72, Ingreso!$B:$D, 3, FALSE), 0), "") -> 1300 | G72: =IF(A72<>"", (D72 - (IFERROR(F72,0) * C72)) - H72 - I72, "") -> 1125.9 | H72: =IF(A72<>"", (D72 - (IFERROR(F72,0) * C72)) * 0.19, "") -> 264.1 | I72: =IF(AND(A72<>"", E72="Tarjeta"), D72 * 0.026, 0) -> 0
A73: 15511 | B73: =IF(A73<>"", IFERROR(VLOOKUP(A73, Ingreso!$B:$H, 2, FALSE), "No existe SKU"), "") -> Individual Tejido Grisazulado 38cm | C73: 8 | D73: =C73*( VLOOKUP(A73,Ingreso!B:G,6,0)) -> 13520 | F73: =IF(A73<>"", IFERROR(VLOOKUP(A73, Ingreso!$B:$D, 3, FALSE), 0), "") -> 800 | G73: =IF(A73<>"", (D73 - (IFERROR(F73,0) * C73)) - H73 - I73, "") -> 5767.2 | H73: =IF(A73<>"", (D73 - (IFERROR(F73,0) * C73)) * 0.19, "") -> 1352.8 | I73: =IF(AND(A73<>"", E73="Tarjeta"), D73 * 0.026, 0) -> 0
A74: XF-69 | B74: =IF(A74<>"", IFERROR(VLOOKUP(A74, Ingreso!$B:$H, 2, FALSE), "No existe SKU"), "") -> Masajeador Corporal recargable | C74: 1 | D74: =C74*( VLOOKUP(A74,Ingreso!B:G,6,0)) -> 2990 | F74: =IF(A74<>"", IFERROR(VLOOKUP(A74, Ingreso!$B:$D, 3, FALSE), 0), "") -> 1000 | G74: =IF(A74<>"", (D74 - (IFERROR(F74,0) * C74)) - H74 - I74, "") -> 1611.9 | H74: =IF(A74<>"", (D74 - (IFERROR(F74,0) * C74)) * 0.19, "") -> 378.1 | I74: =IF(AND(A74<>"", E74="Tarjeta"), D74 * 0.026, 0) -> 0
A75: 8095749 | B75: =IF(A75<>"", IFERROR(VLOOKUP(A75, Ingreso!$B:$H, 2, FALSE), "No existe SKU"), "") -> Salero y Pimentero Cerditos | C75: 1 | D75: =C75*( VLOOKUP(A75,Ingreso!B:G,6,0)) -> 4990 | F75: =IF(A75<>"", IFERROR(VLOOKUP(A75, Ingreso!$B:$D, 3, FALSE), 0), "") -> 2500 | G75: =IF(A75<>"", (D75 - (IFERROR(F75,0) * C75)) - H75 - I75, "") -> 2016.9 | H75: =IF(A75<>"", (D75 - (IFERROR(F75,0) * C75)) * 0.19, "") -> 473.1 | I75: =IF(AND(A75<>"", E75="Tarjeta"), D75 * 0.026, 0) -> 0
A76: XL830L | B76: =IF(A76<>"", IFERROR(VLOOKUP(A76, Ingreso!$B:$H, 2, FALSE), "No existe SKU"), "") -> Humidificador electrico USB | C76: 1 | D76: =C76*( VLOOKUP(A76,Ingreso!B:G,6,0)) -> 3890 | F76: =IF(A76<>"", IFERROR(VLOOKUP(A76, Ingreso!$B:$D, 3, FALSE), 0), "") -> 1900 | G76: =IF(A76<>"", (D76 - (IFERROR(F76,0) * C76)) - H76 - I76, "") -> 1611.9 | H76: =IF(A76<>"", (D76 - (IFERROR(F76,0) * C76)) * 0.19, "") -> 378.1 | I76: =IF(AND(A76<>"", E76="Tarjeta"), D76 * 0.026, 0) -> 0
A77: 6242 | B77: =IF(A77<>"", IFERROR(VLOOKUP(A77, Ingreso!$B:$H, 2, FALSE), "No existe SKU"), "") -> Caja esencias 12 und 3ml | C77: 1 | D77: =C77*( VLOOKUP(A77,Ingreso!B:G,6,0)) -> 2990 | F77: =IF(A77<>"", IFERROR(VLOOKUP(A77, Ingreso!$B:$D, 3, FALSE), 0), "") -> 1500 | G77: =IF(A77<>"", (D77 - (IFERROR(F77,0) * C77)) - H77 - I77, "") -> 1206.9 | H77: =IF(A77<>"", (D77 - (IFERROR(F77,0) * C77)) * 0.19, "") -> 283.1 | I77: =IF(AND(A77<>"", E77="Tarjeta"), D77 * 0.026, 0) -> 0
A78: 808708 | B78: =IF(A78<>"", IFERROR(VLOOKUP(A78, Ingreso!$B:$H, 2, FALSE), "No existe SKU"), "") -> Taza Margarita vidrio | C78: 1 | D78: =C78*( VLOOKUP(A78,Ingreso!B:G,6,0)) -> 3990 | F78: =IF(A78<>"", IFERROR(VLOOKUP(A78, Ingreso!$B:$D, 3, FALSE), 0), "") -> 2000 | G78: =IF(A78<>"", (D78 - (IFERROR(F78,0) * C78)) - H78 - I78, "") -> 1611.9 | H78: =IF(A78<>"", (D78 - (IFERROR(F78,0) * C78)) * 0.19, "") -> 378.1 | I78: =IF(AND(A78<>"", E78="Tarjeta"), D78 * 0.026, 0) -> 0
A79: 808698 | B79: =IF(A79<>"", IFERROR(VLOOKUP(A79, Ingreso!$B:$H, 2, FALSE), "No existe SKU"), "") -> Taza Flores Doble fondo | C79: 2 | D79: =C79*( VLOOKUP(A79,Ingreso!B:G,6,0)) -> 9980 | F79: =IF(A79<>"", IFERROR(VLOOKUP(A79, Ingreso!$B:$D, 3, FALSE), 0), "") -> 2500 | G79: =IF(A79<>"", (D79 - (IFERROR(F79,0) * C79)) - H79 - I79, "") -> 4033.8 | H79: =IF(A79<>"", (D79 - (IFERROR(F79,0) * C79)) * 0.19, "") -> 946.2 | I79: =IF(AND(A79<>"", E79="Tarjeta"), D79 * 0.026, 0) -> 0
A80: 1212 | B80: =IF(A80<>"", IFERROR(VLOOKUP(A80, Ingreso!$B:$H, 2, FALSE), "No existe SKU"), "") -> Bolsa Regalo Dia Mamá | C80: 3 | D80: =C80*( VLOOKUP(A80,Ingreso!B:G,6,0)) -> 1500 | F80: =IF(A80<>"", IFERROR(VLOOKUP(A80, Ingreso!$B:$D, 3, FALSE), 0), "") -> 270 | G80: =IF(A80<>"", (D80 - (IFERROR(F80,0) * C80)) - H80 - I80, "") -> 558.9 | H80: =IF(A80<>"", (D80 - (IFERROR(F80,0) * C80)) * 0.19, "") -> 131.1 | I80: =IF(AND(A80<>"", E80="Tarjeta"), D80 * 0.026, 0) -> 0
A81: 15511 | B81: =IF(A81<>"", IFERROR(VLOOKUP(A81, Ingreso!$B:$H, 2, FALSE), "No existe SKU"), "") -> Individual Tejido Grisazulado 38cm | C81: 4 | D81: =C81*( VLOOKUP(A81,Ingreso!B:G,6,0)) -> 6760 | F81: =IF(A81<>"", IFERROR(VLOOKUP(A81, Ingreso!$B:$D, 3, FALSE), 0), "") -> 800 | G81: =IF(A81<>"", (D81 - (IFERROR(F81,0) * C81)) - H81 - I81, "") -> 2883.6 | H81: =IF(A81<>"", (D81 - (IFERROR(F81,0) * C81)) * 0.19, "") -> 676.4 | I81: =IF(AND(A81<>"", E81="Tarjeta"), D81 * 0.026, 0) -> 0
A82: 61508 | B82: =IF(A82<>"", IFERROR(VLOOKUP(A82, Ingreso!$B:$H, 2, FALSE), "No existe SKU"), "") -> Tetera Infusora Vidrio | C82: 1 | D82: =C82*( VLOOKUP(A82,Ingreso!B:G,6,0)) -> 8590 | F82: =IF(A82<>"", IFERROR(VLOOKUP(A82, Ingreso!$B:$D, 3, FALSE), 0), "") -> 4350 | G82: =IF(A82<>"", (D82 - (IFERROR(F82,0) * C82)) - H82 - I82, "") -> 3434.4 | H82: =IF(A82<>"", (D82 - (IFERROR(F82,0) * C82)) * 0.19, "") -> 805.6 | I82: =IF(AND(A82<>"", E82="Tarjeta"), D82 * 0.026, 0) -> 0
A83: 7676887207875 | B83: =IF(A83<>"", IFERROR(VLOOKUP(A83, Ingreso!$B:$H, 2, FALSE), "No existe SKU"), "") -> Guatero Electrico Conejo Rosado 26x19cm | C83: 1 | D83: =C83*( VLOOKUP(A83,Ingreso!B:G,6,0)) -> 5990 | F83: =IF(A83<>"", IFERROR(VLOOKUP(A83, Ingreso!$B:$D, 3, FALSE), 0), "") -> 2800 | G83: =IF(A83<>"", (D83 - (IFERROR(F83,0) * C83)) - H83 - I83, "") -> 2583.9 | H83: =IF(A83<>"", (D83 - (IFERROR(F83,0) * C83)) * 0.19, "") -> 606.1 | I83: =IF(AND(A83<>"", E83="Tarjeta"), D83 * 0.026, 0) -> 0
A84: 7676887207875 | B84: =IF(A84<>"", IFERROR(VLOOKUP(A84, Ingreso!$B:$H, 2, FALSE), "No existe SKU"), "") -> Guatero Electrico Conejo Rosado 26x19cm | C84: 1 | D84: =C84*( VLOOKUP(A84,Ingreso!B:G,6,0)) -> 5990 | F84: =IF(A84<>"", IFERROR(VLOOKUP(A84, Ingreso!$B:$D, 3, FALSE), 0), "") -> 2800 | G84: =IF(A84<>"", (D84 - (IFERROR(F84,0) * C84)) - H84 - I84, "") -> 2583.9 | H84: =IF(A84<>"", (D84 - (IFERROR(F84,0) * C84)) * 0.19, "") -> 606.1 | I84: =IF(AND(A84<>"", E84="Tarjeta"), D84 * 0.026, 0) -> 0
A85: 61508 | B85: =IF(A85<>"", IFERROR(VLOOKUP(A85, Ingreso!$B:$H, 2, FALSE), "No existe SKU"), "") -> Tetera Infusora Vidrio | C85: 1 | D85: =C85*( VLOOKUP(A85,Ingreso!B:G,6,0)) -> 8590 | F85: =IF(A85<>"", IFERROR(VLOOKUP(A85, Ingreso!$B:$D, 3, FALSE), 0), "") -> 4350 | G85: =IF(A85<>"", (D85 - (IFERROR(F85,0) * C85)) - H85 - I85, "") -> 3434.4 | H85: =IF(A85<>"", (D85 - (IFERROR(F85,0) * C85)) * 0.19, "") -> 805.6 | I85: =IF(AND(A85<>"", E85="Tarjeta"), D85 * 0.026, 0) -> 0
A86: 13935 | B86: =IF(A86<>"", IFERROR(VLOOKUP(A86, Ingreso!$B:$H, 2, FALSE), "No existe SKU"), "") -> Espumador de leche electrico | C86: 1 | D86: =C86*( VLOOKUP(A86,Ingreso!B:G,6,0)) -> 4990 | F86: =IF(A86<>"", IFERROR(VLOOKUP(A86, Ingreso!$B:$D, 3, FALSE), 0), "") -> 2300 | G86: =IF(A86<>"", (D86 - (IFERROR(F86,0) * C86)) - H86 - I86, "") -> 2178.9 | H86: =IF(A86<>"", (D86 - (IFERROR(F86,0) * C86)) * 0.19, "") -> 511.1 | I86: =IF(AND(A86<>"", E86="Tarjeta"), D86 * 0.026, 0) -> 0
A87: 17709-8 | B87: =IF(A87<>"", IFERROR(VLOOKUP(A87, Ingreso!$B:$H, 2, FALSE), "No existe SKU"), "") -> Cargador Inalambrico Magsafe | C87: 1 | D87: =C87*( VLOOKUP(A87,Ingreso!B:G,6,0)) -> 14990 | F87: =IF(A87<>"", IFERROR(VLOOKUP(A87, Ingreso!$B:$D, 3, FALSE), 0), "") -> 12600 | G87: =IF(A87<>"", (D87 - (IFERROR(F87,0) * C87)) - H87 - I87, "") -> 1935.9 | H87: =IF(A87<>"", (D87 - (IFERROR(F87,0) * C87)) * 0.19, "") -> 454.1 | I87: =IF(AND(A87<>"", E87="Tarjeta"), D87 * 0.026, 0) -> 0
A88: 7676887207929 | B88: =IF(A88<>"", IFERROR(VLOOKUP(A88, Ingreso!$B:$H, 2, FALSE), "No existe SKU"), "") -> Guatero Electrico Marron Oso 26x19cm | C88: 1 | D88: =C88*( VLOOKUP(A88,Ingreso!B:G,6,0)) -> 5990 | F88: =IF(A88<>"", IFERROR(VLOOKUP(A88, Ingreso!$B:$D, 3, FALSE), 0), "") -> 2800 | G88: =IF(A88<>"", (D88 - (IFERROR(F88,0) * C88)) - H88 - I88, "") -> 2583.9 | H88: =IF(A88<>"", (D88 - (IFERROR(F88,0) * C88)) * 0.19, "") -> 606.1 | I88: =IF(AND(A88<>"", E88="Tarjeta"), D88 * 0.026, 0) -> 0
A89: 13935 | B89: =IF(A89<>"", IFERROR(VLOOKUP(A89, Ingreso!$B:$H, 2, FALSE), "No existe SKU"), "") -> Espumador de leche electrico | C89: 1 | D89: =C89*( VLOOKUP(A89,Ingreso!B:G,6,0)) -> 4990 | F89: =IF(A89<>"", IFERROR(VLOOKUP(A89, Ingreso!$B:$D, 3, FALSE), 0), "") -> 2300 | G89: =IF(A89<>"", (D89 - (IFERROR(F89,0) * C89)) - H89 - I89, "") -> 2178.9 | H89: =IF(A89<>"", (D89 - (IFERROR(F89,0) * C89)) * 0.19, "") -> 511.1 | I89: =IF(AND(A89<>"", E89="Tarjeta"), D89 * 0.026, 0) -> 0
A90: 7676887207929 | B90: =IF(A90<>"", IFERROR(VLOOKUP(A90, Ingreso!$B:$H, 2, FALSE), "No existe SKU"), "") -> Guatero Electrico Marron Oso 26x19cm | C90: 1 | D90: =C90*( VLOOKUP(A90,Ingreso!B:G,6,0)) -> 5990 | F90: =IF(A90<>"", IFERROR(VLOOKUP(A90, Ingreso!$B:$D, 3, FALSE), 0), "") -> 2800 | G90: =IF(A90<>"", (D90 - (IFERROR(F90,0) * C90)) - H90 - I90, "") -> 2583.9 | H90: =IF(A90<>"", (D90 - (IFERROR(F90,0) * C90)) * 0.19, "") -> 606.1 | I90: =IF(AND(A90<>"", E90="Tarjeta"), D90 * 0.026, 0) -> 0
A91: XF-69 | B91: =IF(A91<>"", IFERROR(VLOOKUP(A91, Ingreso!$B:$H, 2, FALSE), "No existe SKU"), "") -> Masajeador Corporal recargable | C91: 1 | D91: =C91*( VLOOKUP(A91,Ingreso!B:G,6,0)) -> 2990 | F91: =IF(A91<>"", IFERROR(VLOOKUP(A91, Ingreso!$B:$D, 3, FALSE), 0), "") -> 1000 | G91: =IF(A91<>"", (D91 - (IFERROR(F91,0) * C91)) - H91 - I91, "") -> 1611.9 | H91: =IF(A91<>"", (D91 - (IFERROR(F91,0) * C91)) * 0.19, "") -> 378.1 | I91: =IF(AND(A91<>"", E91="Tarjeta"), D91 * 0.026, 0) -> 0
A92: MB058117 | B92: =IF(A92<>"", IFERROR(VLOOKUP(A92, Ingreso!$B:$H, 2, FALSE), "No existe SKU"), "") -> Serum vitamina C 50ml | C92: 1 | D92: =C92*( VLOOKUP(A92,Ingreso!B:G,6,0)) -> 4990 | F92: =IF(A92<>"", IFERROR(VLOOKUP(A92, Ingreso!$B:$D, 3, FALSE), 0), "") -> 2200 | G92: =IF(A92<>"", (D92 - (IFERROR(F92,0) * C92)) - H92 - I92, "") -> 2259.9 | H92: =IF(A92<>"", (D92 - (IFERROR(F92,0) * C92)) * 0.19, "") -> 530.1 | I92: =IF(AND(A92<>"", E92="Tarjeta"), D92 * 0.026, 0) -> 0
A93: MB058116 | B93: =IF(A93<>"", IFERROR(VLOOKUP(A93, Ingreso!$B:$H, 2, FALSE), "No existe SKU"), "") -> Crema vitamina C 50g | C93: 1 | D93: =C93*( VLOOKUP(A93,Ingreso!B:G,6,0)) -> 4990 | F93: =IF(A93<>"", IFERROR(VLOOKUP(A93, Ingreso!$B:$D, 3, FALSE), 0), "") -> 2800 | G93: =IF(A93<>"", (D93 - (IFERROR(F93,0) * C93)) - H93 - I93, "") -> 1773.9 | H93: =IF(A93<>"", (D93 - (IFERROR(F93,0) * C93)) * 0.19, "") -> 416.1 | I93: =IF(AND(A93<>"", E93="Tarjeta"), D93 * 0.026, 0) -> 0
A94: 52507 | B94: =IF(A94<>"", IFERROR(VLOOKUP(A94, Ingreso!$B:$H, 2, FALSE), "No existe SKU"), "") -> Audifonos Airpods Pro 2 | C94: 1 | D94: =C94*( VLOOKUP(A94,Ingreso!B:G,6,0)) -> 24990 | F94: =IF(A94<>"", IFERROR(VLOOKUP(A94, Ingreso!$B:$D, 3, FALSE), 0), "") -> 13680 | G94: =IF(A94<>"", (D94 - (IFERROR(F94,0) * C94)) - H94 - I94, "") -> 9161.1 | H94: =IF(A94<>"", (D94 - (IFERROR(F94,0) * C94)) * 0.19, "") -> 2148.9 | I94: =IF(AND(A94<>"", E94="Tarjeta"), D94 * 0.026, 0) -> 0
A95: 52507 | B95: =IF(A95<>"", IFERROR(VLOOKUP(A95, Ingreso!$B:$H, 2, FALSE), "No existe SKU"), "") -> Audifonos Airpods Pro 2 | C95: 1 | D95: =C95*( VLOOKUP(A95,Ingreso!B:G,6,0)) -> 24990 | F95: =IF(A95<>"", IFERROR(VLOOKUP(A95, Ingreso!$B:$D, 3, FALSE), 0), "") -> 13680 | G95: =IF(A95<>"", (D95 - (IFERROR(F95,0) * C95)) - H95 - I95, "") -> 9161.1 | H95: =IF(A95<>"", (D95 - (IFERROR(F95,0) * C95)) * 0.19, "") -> 2148.9 | I95: =IF(AND(A95<>"", E95="Tarjeta"), D95 * 0.026, 0) -> 0
A96: 17709-8 | B96: =IF(A96<>"", IFERROR(VLOOKUP(A96, Ingreso!$B:$H, 2, FALSE), "No existe SKU"), "") -> Cargador Inalambrico Magsafe | C96: 1 | D96: =C96*( VLOOKUP(A96,Ingreso!B:G,6,0)) -> 14990 | F96: =IF(A96<>"", IFERROR(VLOOKUP(A96, Ingreso!$B:$D, 3, FALSE), 0), "") -> 12600 | G96: =IF(A96<>"", (D96 - (IFERROR(F96,0) * C96)) - H96 - I96, "") -> 1935.9 | H96: =IF(A96<>"", (D96 - (IFERROR(F96,0) * C96)) * 0.19, "") -> 454.1 | I96: =IF(AND(A96<>"", E96="Tarjeta"), D96 * 0.026, 0) -> 0
A97: 13517 | B97: =IF(A97<>"", IFERROR(VLOOKUP(A97, Ingreso!$B:$H, 2, FALSE), "No existe SKU"), "") -> Huevera Plastica | C97: 1 | D97: =C97*( VLOOKUP(A97,Ingreso!B:G,6,0)) -> 5290 | F97: =IF(A97<>"", IFERROR(VLOOKUP(A97, Ingreso!$B:$D, 3, FALSE), 0), "") -> 2400 | G97: =IF(A97<>"", (D97 - (IFERROR(F97,0) * C97)) - H97 - I97, "") -> 2340.9 | H97: =IF(A97<>"", (D97 - (IFERROR(F97,0) * C97)) * 0.19, "") -> 549.1 | I97: =IF(AND(A97<>"", E97="Tarjeta"), D97 * 0.026, 0) -> 0
A98: 13517 | B98: =IF(A98<>"", IFERROR(VLOOKUP(A98, Ingreso!$B:$H, 2, FALSE), "No existe SKU"), "") -> Huevera Plastica | C98: 1 | D98: =C98*( VLOOKUP(A98,Ingreso!B:G,6,0)) -> 5290
A99: 13517 | B99: =IF(A99<>"", IFERROR(VLOOKUP(A99, Ingreso!$B:$H, 2, FALSE), "No existe SKU"), "") -> Huevera Plastica | C99: 1 | D99: =C99*( VLOOKUP(A99,Ingreso!B:G,6,0)) -> 5290
A100: 52507 | B100: =IF(A100<>"", IFERROR(VLOOKUP(A100, Ingreso!$B:$H, 2, FALSE), "No existe SKU"), "") -> Audifonos Airpods Pro 2 | C100: 1 | D100: =C100*( VLOOKUP(A100,Ingreso!B:G,6,0)) -> 24990
A101: 7676887207875 | B101: =IF(A101<>"", IFERROR(VLOOKUP(A101, Ingreso!$B:$H, 2, FALSE), "No existe SKU"), "") -> Guatero Electrico Conejo Rosado 26x19cm | C101: 1 | D101: =C101*( VLOOKUP(A101,Ingreso!B:G,6,0)) -> 5990
A102: 19571 | B102: =IF(A102<>"", IFERROR(VLOOKUP(A102, Ingreso!$B:$H, 2, FALSE), "No existe SKU"), "") -> Cesta Ropa Cuadrada café con tapa 42*30*56cm | C102: 1 | D102: =C102*( VLOOKUP(A102,Ingreso!B:G,6,0)) -> 15290
A103: 11409 | B103: =IF(A103<>"", IFERROR(VLOOKUP(A103, Ingreso!$B:$H, 2, FALSE), "No existe SKU"), "") -> Bolsa lavadora 40x50cm | C103: 1 | D103: =C103*( VLOOKUP(A103,Ingreso!B:G,6,0)) -> 1890
A104: 11409 | B104: =IF(A104<>"", IFERROR(VLOOKUP(A104, Ingreso!$B:$H, 2, FALSE), "No existe SKU"), "") -> Bolsa lavadora 40x50cm | C104: 2 | D104: =C104*( VLOOKUP(A104,Ingreso!B:G,6,0)) -> 3780
A105: 24049 | B105: =IF(A105<>"", IFERROR(VLOOKUP(A105, Ingreso!$B:$H, 2, FALSE), "No existe SKU"), "") -> Camino de mesa blanco gris 35x180cm | C105: 1 | D105: =C105*( VLOOKUP(A105,Ingreso!B:G,6,0)) -> 5790
A106: 1010 | B106: =IF(A106<>"", IFERROR(VLOOKUP(A106, Ingreso!$B:$H, 2, FALSE), "No existe SKU"), "") -> Centrifuga para ensaladas | C106: 1 | D106: =C106*( VLOOKUP(A106,Ingreso!B:G,6,0)) -> 9690
...

Sheet Pedidos
A1: Maria | B1: 36540 | D1: Entregado | E1: transferencia
A2: Cinthya | B2: 9180 | D2: Entregado | E2: efectivo
A3: Ely | B3: 9580 | D3: Entregado | E3: transferencia
A4: wendy | B4: 9880 | D4: Entregado | E4: transferencia
A5: Armando | B5: 27680 | D5: Entregado | E5: efectivo
A6: Priscila | B6: 9690 | D6: Entregado | E6: transferencia
A7: Pablo | B7: 15290 | D7: Entregado | E7: transferencia
A8: cliente | B8: 47650 | D8: Entregado | E8: pagado
A9: cliente | B9: 7890 | D9: Entregado | E9: transferencia
A10: mama faby | B10: 18010 | D10: Entregado | E10: transferencia
A11: ivan | B11: 7080 | D11: Entregado | E11: tarjeta
A12: Faby | B12: 3890 | D12: Entregado | E12: tarjeta
... A18: Anais | B18: 30540 | D18: Entregado | E18: tarjeta
A19: ximena | B19: 21950 | D19: Entregado | E19: tarjeta | I19: matias | J19: 20580
A20: Ximena | B20: 5290 | D20: Entregado | E20: tarjeta | I20: omar | J20: 28960
A21: Lily | B21: 3990 | D21: Entregado | I21: Cinthya | J21: 20340
A22: Sr. Maria | B22: 13520 | D22: Entregado | E22: transferencia | I22: josefa | J22: 15000
A23: Cinthya | B23: 7780 | C23: 2 humidificadores rosados | D23: Entregado | E23: transferencia | I23: Ivana | J23: 5290
A24: Fernando | B24: 14860 | D24: Entregado | E24: transferencia | I24: matias | J24: 25000
A25: Cinthya | B25: 6760 | D25: Entregado | I25: Tamy | J25: 1990
J26: =SUM(J19:J25) -> 117160
A27: MAYO
A28: Sr. Maria | B28: 15470 | C28: 1 taza margarita, 2 taza flor, 3 bolsas mamá | D28: Entregado | E28: transferencia
A29: Wendy | B29: 8590 | C29: 1 tetera | D29: Entregado | E29: transferencia
A30: Mabel | B30: 5990 | C30: Guatero elec, conejo | D30: Entregado | E30: transferencia
A31: Tabita | B31: 5990 | C31: Guatero elec, conejo | D31: Entregado | E31: transferencia
A32: Cinthya | B32: 13580+6760 | C32: Tetera y espumador electrico | D32: Pendiente | E32: paga junto a los individuales (20.340)
A33: Josefa | B33: 15000 | C33: Cargador magsafe | D33: Pendiente | E33: Pago Pendiente
A34: Maria | B34: 5990 | C34: Guatero elec. oso | D34: Entregado | E34: transferencia
A35: Ivan | B35: 22970 | C35: pack vitamina c, guatero elec. oso, espumador leche, masajeador | D35: Entregado | E35: tarjeta
A36: Hernol | B36: 25000 | C36: audifonos | D36: Entregado | E36: transferencia
A37: Dafnne | B37: 45290 | C37: 1 audifono, 1 cargador, 1 huevera | D37: Entregado | E37: transferencia
A38: Wendy | B38: 5290 | C38: 1 huevera | D38: Entregado | E38: transferencia
A39: Ivana | B39: 5290 | C39: 1 huevera | D39: Pendiente
A40: Maty | B40: 25000 | C40: 1 audifono | D40: Pendiente
A41: Seba | B41: 23170 | C41: 1 guatero elec. conejo 1 cesta gris, 1 bolsa lavado | D41: Entregado | E41: tarjeta
A42: Ximena | B42: 9570 | C42: 2 bolsa lavado 1 camino mesa | D42: Entregado | E42: tarjeta
A43: Tamy | B43: 1990 | C43: exprimidor | D43: Entregado | E43: pendiente
A44: Mama rosa | B44: 22860 | C44: 1 centrifuga 1 lechero 1 mielero 1 colgante pajaro | D44: Entregado | E44: tarjeta
A45: Liliana | B45: 5990 | C45: 1 guatero elec. oso | D45: Entregado | E45: transferencia
A46: Maria | B46: 13520 | C46: 8 individuales azules | D46: Entregado | E46: transferencia
A47: Antonio | B47: 15000 | C47: 1 cargador | D47: Entregado | E47: transferencia
A48: Cliente | B48: 25000 | C48: 1 audifono | D48: Entregado | E48: transferencia
A49: Pablo | B49: 25000 | C49: 1 audifono | D49: Entregado | E49: transferencia
A50: Pablo | B50: 25000 | C50: 1 audifono | D50: Entregado | E50: transferencia
